{
    "data": {
        "wiki": [
            {
                "datetime": "2024年08月19日 11時の問題",
                "url": "https://ja.wikipedia.org/?curid=339023",
                "title": "ズレチェ",
                "text": "〇〇は、スロベニアの市である。"
            },
            {
                "datetime": "2024年08月19日 10時の問題",
                "url": "https://ja.wikipedia.org/?curid=614513",
                "title": "高橋大斗",
                "text": "〇〇は、秋田県北秋田市出身のノルディック複合、ジャンプ選手。現役時代は土屋ホームに所属していた。"
            },
            {
                "datetime": "2024年08月19日 08時の問題",
                "url": "https://ja.wikipedia.org/?curid=704062",
                "title": "アミューズメントミューズ1/3娘",
                "text": "〇〇は、2006年4月4日から2007年3月31日まで日本テレビで放送されていたバラエティ番組である。EPGによっては「アイドル育成1/3娘」となっていた。放送時間は毎日月曜日から木曜日が25:26 - 25:35、金曜日が25:45 - 25:54であったが、他の番組など編成上の都合で変更になることが多かった。回数は2006年8月19日放送分で100回目、2007年1月13日放送分で200回目を達成し、かつて同時間に放送されていた「エンパラナイト」に次ぐ長寿ミニ番組となった。"
            },
            {
                "datetime": "2024年08月19日 07時の問題",
                "url": "https://ja.wikipedia.org/?curid=4588390",
                "title": "阿久根潤",
                "text": "〇〇は、日本の元ラグビーユニオン選手、俳優。現在トップイーストリーグAグループ東京ガスラグビー部の育成プログラムプロジェクトリーダーを務めている。"
            },
            {
                "datetime": "2024年08月19日 06時の問題",
                "url": "https://ja.wikipedia.org/?curid=56903",
                "title": "公妾",
                "text": "〇〇は、結婚の秘跡に反するために離婚と並んで側室制度が許されなかったキリスト教ヨーロッパ諸国の宮廷で主に近世に採用された歴史的制度。'Maîtresse royale'（仏、英:Royal mistress、王の愛人）から訳された歴史用語。寵姫。"
            },
            {
                "datetime": "2024年08月19日 05時の問題",
                "url": "https://ja.wikipedia.org/?curid=384832",
                "title": "名曲喫茶",
                "text": "〇〇は、喫茶店やカフェの業態のひとつ。店内に設置した音響機器によりクラシック音楽のレコードを再生し、コーヒーや軽食とともに音楽鑑賞の場を客に提供するものを指す。店内に静粛さが求められることから、酒類を提供しない純喫茶の業態をとることが多い。"
            },
            {
                "datetime": "2024年08月19日 04時の問題",
                "url": "https://ja.wikipedia.org/?curid=3527338",
                "title": "イオン散乱",
                "text": "〇〇は、物質に入射したイオンが物質によって散乱される現象のこと。〇〇を用いた固体の構造解析手法は、入射イオンのエネルギーによって大きく二つに分けられる。低速〇〇分光 (low-energy ion scattering spectroscopy)keV領域の低エネルギーのイオンを照射する方法。単に〇〇分光(ISS, Ion Scattering Spectroscopy)と言ったときは、この低速〇〇分光のことを意味することが多い。ラザフォード後方散乱分光(RBS, Rutherford Backscattering spectroscopy)MeV領域の高エネルギーのイオンを照射する方法。"
            },
            {
                "datetime": "2024年08月19日 03時の問題",
                "url": "https://ja.wikipedia.org/?curid=2644615",
                "title": "第35回セザール賞",
                "text": "〇〇は、2009年の映画を対象としており、授賞式は2010年2月27日に開催された。授賞式のプレジデントはマリオン・コティヤールである。"
            },
            {
                "datetime": "2024年08月19日 02時の問題",
                "url": "https://ja.wikipedia.org/?curid=105703",
                "title": "村上市",
                "text": "〇〇は、新潟県北部にある市。日本海に面している。北限の茶どころとして知られるほか、三面川の鮭や牛肉（村上牛）が名物。瀬波温泉や笹川流れ、町屋通り、粟島航路など観光都市としての側面が強い。〇〇街地は村上藩の城下町として栄え、現在でも市中に武家町、商人町の面影が残る。中心街では町屋再生などの各種プロジェクトが進んでおり、2008年度には都市景観大賞｢美しいまちなみ大賞｣を受賞、2016年には「プロジェクト未来遺産2016」に選定されている。"
            },
            {
                "datetime": "2024年08月19日 01時の問題",
                "url": "https://ja.wikipedia.org/?curid=1046923",
                "title": "マルターノ",
                "text": "〇〇は、イタリア共和国プッリャ州レッチェ県にある、人口約9,000人の基礎自治体（コムーネ）。"
            },
            {
                "datetime": "2024年08月19日 00時の問題",
                "url": "https://ja.wikipedia.org/?curid=3288016",
                "title": "スタニスラス",
                "text": "〇〇は、スラヴ語起源のフランス語圏の男性名。スタニスラフ、スタニスワフのフランス語形にあたる。"
            },
            {
                "datetime": "2024年08月18日 23時の問題",
                "url": "https://ja.wikipedia.org/?curid=4915449",
                "title": "九鬼隆治",
                "text": "〇〇は、日本の旧華族（子爵）である。綾部藩10代藩主・九鬼隆備の長男であり、綾部九鬼家11代当主。皇道宣揚会（高御位神宮）の創設者。"
            },
            {
                "datetime": "2024年08月18日 22時の問題",
                "url": "https://ja.wikipedia.org/?curid=3999931",
                "title": "千葉光行",
                "text": "〇〇は、日本の政治家、歯科医師。第22代千葉県市川市長（3期）を務めた。"
            },
            {
                "datetime": "2024年08月18日 21時の問題",
                "url": "https://ja.wikipedia.org/?curid=4218813",
                "title": "ロングテイルホップマウス",
                "text": "〇〇は、齧歯目ネズミ科に属するネズミの一種である。オーストラリア大陸に広く棲息していたが、すでに絶滅した。1844年にジョン・グールドによって最初に記録された。"
            },
            {
                "datetime": "2024年08月18日 20時の問題",
                "url": "https://ja.wikipedia.org/?curid=3721382",
                "title": "竹東駅 (慶尚北道)",
                "text": "〇〇は、大韓民国慶尚北道慶州市にかつて存在した韓国鉄道公社東海線（旧東海南部線）の駅である。"
            },
            {
                "datetime": "2024年08月18日 19時の問題",
                "url": "https://ja.wikipedia.org/?curid=483138",
                "title": "広州地下鉄1号線",
                "text": "〇〇は、中華人民共和国広東省広州市天河区の広州東駅から茘湾区の西塱駅までを結ぶ広州地下鉄の路線。広州地鉄集団有限公司が運営する。ラインカラーは■黄色。路線距離18.497キロ、南北－東西方向で16駅、1車両基地がある。6両編成のA型列車を使用している。1号線は広州初の地下鉄路線である。"
            },
            {
                "datetime": "2024年08月18日 18時の問題",
                "url": "https://ja.wikipedia.org/?curid=3880066",
                "title": "松田邦紀",
                "text": "〇〇は、日本の外交官。香港大使兼総領事や、駐パキスタン特命全権大使等を経て、2021年より駐ウクライナ特命全権大使。但し、2022年に始まったロシア・ウクライナ戦争が激化してからは、一時、隣国ポーランドのジェシュフに設置された連絡事務所を拠点に執務を行っていた。"
            },
            {
                "datetime": "2024年08月18日 17時の問題",
                "url": "https://ja.wikipedia.org/?curid=3701709",
                "title": "ヴィクトリア朝のバーレスク",
                "text": "〇〇は、19世紀半ばのヴィクトリア朝イングランド及びニューヨークの劇場で人気があった舞台エンタテイメントの一ジャンルである。時としてトラヴェスティやエクストラバガンザなどと呼ばれることもある。よく知られたオペラや古典戯曲、バレエなどを大ざっばな喜劇に翻案したパロディの一種で、通常はきわどい内容の音楽劇であり、原作の演劇的あるいは音楽的なコンヴェンションやスタイルを諷刺するものである。しばしば原作のテクストや音楽を引用し、パスティーシュにする。〇〇は、バーレスクの一種である。バラッド・オペラ同様、バーレスクの音楽は人気のあった同時代の楽曲からオペラのアリアまで、幅広い音楽に拠っていたが、1880年代以降の後期のバーレスクではオリジナルの曲を使用することもあった。多くの演目はエクストラバガンザとして上演されていたため、ダンスが重要な役割を果たし、演出、衣装その他の脚色の見世物的要素が非常に注目されることとなった。男役の大部分は、肉体的魅力を見せるためにわざと女優がズボン役で演じており、老いた女性の役は男優が演じることもあった。もともとは短い一幕物だったが、バーレスクはのちにもっと長い演目になり、一晩のプログラムのほとんどか全部を占めるようになった。バーレスクの作家としてはJ・R・プランシェ、H・J・バイロン、G・R・シムズ、F・C・バーナンド、ウィリアム・S・ギルバート、フレッド・レズリーなどがいる。"
            },
            {
                "datetime": "2024年08月18日 16時の問題",
                "url": "https://ja.wikipedia.org/?curid=435506",
                "title": "胎児危険度分類",
                "text": "〇〇は、医薬品による胎児傷害の危険性に対する見積もりであり、妊婦が用いた場合を想定している。つまり、人乳中へ移行した薬剤に対する危険性を扱うものではないし、医薬品に伴う全ての危険性を扱うものでもない。類似する分類として授乳危険度分類という指針がある。日本における公的な〇〇は存在しない。このため、国内の実地診療ではアメリカ食品医薬品局 (FDA) による分類や、オーストラリアの分類などを参考に判断されることが多い。添付文書における文言の僅かな差異は、胎児に対する危険度を含意する内容になっているが、統一的な危険性の階層化が成されていない。虎の門病院は独自の基準を公表している。"
            },
            {
                "datetime": "2024年08月18日 15時の問題",
                "url": "https://ja.wikipedia.org/?curid=4235210",
                "title": "吉田茂 (野球)",
                "text": "〇〇は、日本の元アマチュア野球選手である。ポジションは投手。"
            },
            {
                "datetime": "2024年08月18日 14時の問題",
                "url": "https://ja.wikipedia.org/?curid=2540751",
                "title": "コパ・リベルタドーレス1972",
                "text": "〇〇は、13回目のコパ・リベルタドーレスである。インデペンディエンテ（アルゼンチン）がウニベルシタリオ（ペルー）を決勝で下し、大会史上2チーム目となる3回目の優勝を飾った。"
            },
            {
                "datetime": "2024年08月18日 13時の問題",
                "url": "https://ja.wikipedia.org/?curid=417328",
                "title": "国鉄ED57形電気機関車",
                "text": "〇〇は、日本国有鉄道（国鉄）の前身である鉄道省がドイツから輸入した直流用電気機関車である。国鉄最後の輸入電気機関車となった。"
            },
            {
                "datetime": "2024年08月18日 12時の問題",
                "url": "https://ja.wikipedia.org/?curid=177323",
                "title": "あおなみカード",
                "text": "〇〇は、名古屋臨海高速鉄道が発行していた乗車カードである。あおなみ線各駅の乗車券自動券売機で販売していた。ストアードフェアシステムに対応しており、トランパス加盟各社局で使用できた。2011年2月11日にICカード「manaca」が導入されたことに伴い、前日の10日をもって発売終了、翌2012年2月29日で利用終了となった。"
            },
            {
                "datetime": "2024年08月18日 11時の問題",
                "url": "https://ja.wikipedia.org/?curid=2885462",
                "title": "バンガー (北アイルランド)",
                "text": "〇〇は、イギリス、北アイルランドのアーズ・アンド・ノース・ダウン行政区の中心都市。2015年の人口は6万2460人。面積は19.56km2。人口密度は3193.3人/km2。"
            },
            {
                "datetime": "2024年08月18日 10時の問題",
                "url": "https://ja.wikipedia.org/?curid=1562246",
                "title": "男達のメロディー",
                "text": "〇〇は、1979年4月21日に、CBSソニーから発売されたSHŌGUNのシングル。"
            },
            {
                "datetime": "2024年08月18日 08時の問題",
                "url": "https://ja.wikipedia.org/?curid=561649",
                "title": "大分発電所",
                "text": "〇〇は、大分県大分市大字一の洲1-2にあった九州電力の火力発電所。"
            },
            {
                "datetime": "2024年08月18日 07時の問題",
                "url": "https://ja.wikipedia.org/?curid=19355",
                "title": "摂津国",
                "text": "〇〇は、日本の令制国の一つで、瀬戸内海の東端と紀伊半島の北西端を占める地域。現在の大阪府北中部の大半と兵庫県南東部に当たり、大阪市と神戸市とその周辺なので阪神（はんしん）と呼ばれることもある。"
            },
            {
                "datetime": "2024年08月18日 06時の問題",
                "url": "https://ja.wikipedia.org/?curid=450535",
                "title": "小野坂・伊福部のUNHAPPY",
                "text": "〇〇は、声優の小野坂昌也と放送作家の伊福部崇がパーソナリティを務めるラジオ番組である。文化放送、BBQR等で放送されている。"
            },
            {
                "datetime": "2024年08月18日 05時の問題",
                "url": "https://ja.wikipedia.org/?curid=4764013",
                "title": "MDC1",
                "text": "〇〇は、ヒトでは6番染色体短腕（p）に位置する〇〇遺伝子にコードされる、2080アミノ酸からなるタンパク質である。〇〇はS期内チェックポイントとG2/M期チェックポイントの調節因子であり、DNA損傷部位へ修復タンパク質をリクルートする。また、がん抑制タンパク質p53と結合し、細胞生存運命の決定にも関与する。このタンパク質はNFBD1（nuclear factor with BRCT domain 1）という別名でも知られる。"
            },
            {
                "datetime": "2024年08月18日 04時の問題",
                "url": "https://ja.wikipedia.org/?curid=1598058",
                "title": "知多半島ユースホステル",
                "text": "〇〇は、愛知県知多郡美浜町にあったユースホステル。日本ユースホステル協会に加盟していた。無期限休館を経てユースホステルとしては閉館した。また、ティレク・ティレセク美浜美術館、カフェ・エリオットを併設している。"
            },
            {
                "datetime": "2024年08月18日 03時の問題",
                "url": "https://ja.wikipedia.org/?curid=4089968",
                "title": "大野季夫",
                "text": "〇〇は、昭和時代の内務官僚。拓務官僚。朝鮮総督府官僚。慶尚南道知事。"
            },
            {
                "datetime": "2024年08月18日 02時の問題",
                "url": "https://ja.wikipedia.org/?curid=283985",
                "title": "呼吸器学",
                "text": "〇〇は、主に人体の呼吸器系を中心に診療・研究する内科学の一分野。元々の語源である「pulmonology（肺学、肺臓学）」からわかるように、主に肺を扱っていった分野として発展していった。呼吸器外科学と連携して治療にあたっており、診療科としては呼吸器内科と呼吸器外科が共に呼吸器センターを設置している施設もある。"
            },
            {
                "datetime": "2024年08月18日 01時の問題",
                "url": "https://ja.wikipedia.org/?curid=888723",
                "title": "ロディオン・ガタウリン",
                "text": "〇〇は、ソビエト連邦・ウズベク共和国タシケント出身の陸上競技選手（ソ連崩壊後はロシア代表）。1988年ソウルオリンピック棒高跳の銀メダリストである。1989年1月、ガタウリンは室内で6m00を記録し、セルゲイ・ブブカに次いで2番目に6m00に到達した。同時にこれは、室内では史上初めて6m00に到達した跳躍となった。2月には自己の室内世界記録を更新する6m02を記録。その後はブブカに抜かれたものの、この記録は2014年7月現在でも室内世界歴代4位の記録である。9月には屋外でも6m00をマークした。"
            },
            {
                "datetime": "2024年08月18日 00時の問題",
                "url": "https://ja.wikipedia.org/?curid=4588338",
                "title": "松苧神社",
                "text": "〇〇は、新潟県十日町市犬伏（いぬぶし）の松苧山にある神社。「松苧大権現」とも呼ばれる。本項では、犬伏の〇〇以外にも、平成の大合併後の十日町市を中心とした地域に点在している〇〇にも触れる。"
            },
            {
                "datetime": "2024年08月17日 23時の問題",
                "url": "https://ja.wikipedia.org/?curid=1498842",
                "title": "ジャマイカの行政区画",
                "text": "〇〇は、3つの郡 (county) に分割され、さらに14の行政教区 (Parish) に分かれる。"
            },
            {
                "datetime": "2024年08月17日 22時の問題",
                "url": "https://ja.wikipedia.org/?curid=15616",
                "title": "東久邇宮稔彦王",
                "text": "〇〇は、日本の旧皇族、政治家、陸軍軍人。東久邇宮初代当主。陸士20期・陸大26期。最終階級は陸軍大将。位階勲等功級は従二位大勲位功一級。第二次世界大戦後、終戦処理内閣として内閣総理大臣（在職1945年8月17日-1945年10月9日）に就任。憲政史上唯一の皇族内閣を組閣。内閣総理大臣として、連合国に対する降伏文書の調印、軍の解体と復員、行政機構の平時化、占領軍受け入れなどを実施した。しかし、自由化政策を巡るGHQと内務省による対立やGHQによる内政干渉に対し、抵抗の意志を示すため総辞職した。在任日数54日間は、長らく内閣制度史上最短記録であった。内閣総理大臣退任後の1946年（昭和21年）に公職追放となり、1947年（昭和22年）に臣籍降下した。1950年（昭和25年）には新興宗教「ひがしくに教」を立ち上げて一時教祖となった。しかし手がけた事業はことごとく失敗した。歴代内閣総理大臣の中の最長寿者（102歳48日=37303日で死去）。千葉工業大学の創設に当たってはその発案者となった人物。香淳皇后は姪、第125代天皇・明仁（上皇）は従孫に当たる。"
            },
            {
                "datetime": "2024年08月17日 21時の問題",
                "url": "https://ja.wikipedia.org/?curid=973845",
                "title": "イブン・ハイサム",
                "text": "〇〇は、イスラム圏の数学者、天文学者、物理学者、医学者、哲学者、音楽学者（965年 - 1040年）。〇〇は光学の諸原理の発見と科学実験手法の発展に対し、近代科学へ重要な貢献をした人物である。また彼が残した光学に関する書物、レンズや鏡を使った屈折や反射の実験などから「光学の父」ともみなされている。「アルハゼンの定理」や月のクレーター「アルハゼン」は彼にちなむ。"
            },
            {
                "datetime": "2024年08月17日 20時の問題",
                "url": "https://ja.wikipedia.org/?curid=4207711",
                "title": "朱永植",
                "text": "〇〇は、朝鮮民主主義人民共和国の政治家。朝鮮労働党中央委員会委員、朝鮮労働党軍需工業部長(推定)。慈江道党委員会責任書記、平壌直轄市党委員会書記などを歴任した。"
            },
            {
                "datetime": "2024年08月17日 19時の問題",
                "url": "https://ja.wikipedia.org/?curid=3763750",
                "title": "近藤万春",
                "text": "〇〇は、福岡県福岡市出身のハンドボール選手。日本ハンドボールリーグのイズミメイプルレッズ所属。"
            },
            {
                "datetime": "2024年08月17日 18時の問題",
                "url": "https://ja.wikipedia.org/?curid=1869770",
                "title": "トラビス・スナイダー",
                "text": "〇〇は、アメリカ合衆国ワシントン州スノホミッシュ郡エバレット出身の元プロ野球選手（外野手）。左投左打。愛称はランチボックス。"
            }
        ]
    }
}