{
    "data": {
        "wiki": [
            {
                "datetime": "2025年06月17日 09時の問題",
                "url": "https://ja.wikipedia.org/?curid=621890",
                "title": "鹹水",
                "text": "〇〇は、塩化ナトリウムなどの塩分を含んだ水である。代表的な〇〇は海水であり、海水との境界に存在する汽水も〇〇に含まれる。また、過去に海水が閉じ込められてできた化石水、岩塩地帯の塩分を含んだ水など、陸水にも〇〇が存在する。対義語は淡水。〇〇の中でしか生きられない魚類のことを〇〇魚という。"
            },
            {
                "datetime": "2025年06月17日 08時の問題",
                "url": "https://ja.wikipedia.org/?curid=997206",
                "title": "アレクサンドル・ヴラジスラブレフ",
                "text": "〇〇は、ソビエト連邦およびロシアの実業家、政治家。モスクワ出身。ロシア産業企業家同盟副議長、国際関係委員長、教育大臣および下院議員を歴任。"
            },
            {
                "datetime": "2025年06月17日 07時の問題",
                "url": "https://ja.wikipedia.org/?curid=1513050",
                "title": "主イエスの変容",
                "text": "〇〇は、福音書に記述された、イエス・キリストが高い山に弟子たち（ペトロ、ヨハネ、ヤコブ）を伴い、旧約の預言者であるモーセとエリヤと語り合いながら白く光り輝く姿を弟子たちに示したと聖書に記された出来事をいう（マタイによる福音書17章1節 - 9節、マルコによる福音書9章2節 - 8節、ルカによる福音書9章28節 - 36節）。"
            },
            {
                "datetime": "2025年06月17日 06時の問題",
                "url": "https://ja.wikipedia.org/?curid=120915",
                "title": "ゴルディアヌス1世",
                "text": "〇〇は、マルクス・アントニウス・ゴルディアヌス・センプロニアヌス・ロマヌス・アフリカヌス・アウグストゥス（ラテン語: Marcus Antonius Gordianus Sempronianus Romanus Africanus Augustus, 159年頃 - 238年4月12日）は、ローマ帝国の軍人皇帝である。"
            },
            {
                "datetime": "2025年06月17日 05時の問題",
                "url": "https://ja.wikipedia.org/?curid=4331628",
                "title": "コディ・ウォーカー",
                "text": "〇〇は、アメリカ合衆国カリフォルニア州出身の俳優。ポール・ウォーカーの弟でもあり、ポールの死後に彼の遺作である第7作『ワイルド・スピード SKY MISSION』にポールの演じていたブライアン・オコナー役で出演し作品を完成させた。演技でのデビュー作は『Abandoned Mine (en) 、廃鉱山』（2013年）。俳優としてのデビュー作は『パシフィック・ウォー』（2016年）。"
            },
            {
                "datetime": "2025年06月17日 04時の問題",
                "url": "https://ja.wikipedia.org/?curid=2743246",
                "title": "ミュージック・ファーマー 武田鉄矢・元気です!",
                "text": "〇〇は、1993年10月2日までは毎週土曜17:00〜18:00、1993年10月10日以降は毎週日曜16:30〜17:30。あらゆる“古今東西”をテーマにして、放送していた。"
            },
            {
                "datetime": "2025年06月17日 03時の問題",
                "url": "https://ja.wikipedia.org/?curid=3739926",
                "title": "SCREEN mode SOUL on the radio",
                "text": "〇〇は、2017年1月2日から東海ラジオ放送で放送していたラジオ番組。放送時間は毎週日曜 23:30 - 24:00。"
            },
            {
                "datetime": "2025年06月17日 02時の問題",
                "url": "https://ja.wikipedia.org/?curid=4055081",
                "title": "日向正宗",
                "text": "〇〇は、鎌倉時代に作られたとされる日本刀（短刀）。日本の国宝に指定されている。東京都中央区日本橋室町にある三井記念美術館が所蔵する。また、後述の経緯から大垣正宗とも呼ばれる。"
            },
            {
                "datetime": "2025年06月17日 01時の問題",
                "url": "https://ja.wikipedia.org/?curid=2336077",
                "title": "堀田一継",
                "text": "〇〇は、安土桃山時代の武将。江戸時代初期の旗本。豊臣秀吉の鷹匠頭。秀吉と徳川家康、秀忠の御伽衆。諱は重武ともいう。通称は、孫七、権右衛門、若狭守。"
            },
            {
                "datetime": "2025年06月17日 00時の問題",
                "url": "https://ja.wikipedia.org/?curid=4061358",
                "title": "清水大輔 (クリエイター)",
                "text": "〇〇は、日本の映像タイムラプスクリエイター。福島県いわき市出身。日本初のタイムラプスハイパーラプス専門クリエイター。NHKの番組「TIME-LAPSE JAPAN」「福島タイムラプス」「そこにある光」の映像制作と主演をしている。また東芝メモリのCMに起用されている。2019年11月には日本初のタイムラプスハイパーラプス個展 を開催。"
            },
            {
                "datetime": "2025年06月16日 23時の問題",
                "url": "https://ja.wikipedia.org/?curid=3341686",
                "title": "能條ジョー",
                "text": "〇〇は、日本の構成作家。2015年から2019年まで、南インド・チェンナイで本格日本式ラーメン店「AKI BAY 秋平」の運営。"
            },
            {
                "datetime": "2025年06月16日 22時の問題",
                "url": "https://ja.wikipedia.org/?curid=546867",
                "title": "カルメン・エレクトラ",
                "text": "〇〇は、アメリカ合衆国のモデル・女優。オハイオ州・シンシナティ郊外の出身。アイルランド・ドイツ・チェロキーの血を引いている。"
            },
            {
                "datetime": "2025年06月16日 21時の問題",
                "url": "https://ja.wikipedia.org/?curid=1758161",
                "title": "ブラッド・ジーグラー",
                "text": "〇〇は、アメリカ合衆国カンザス州プラット郡プラット出身の元プロ野球選手（投手）。右投右打。愛称はユニコーン（Unicorn）。"
            },
            {
                "datetime": "2025年06月16日 20時の問題",
                "url": "https://ja.wikipedia.org/?curid=3786173",
                "title": "ムエ",
                "text": "〇〇は、フランス、ペイ・ド・ラ・ロワール地域圏、ロワール＝アトランティック県のコミューン。"
            },
            {
                "datetime": "2025年06月16日 19時の問題",
                "url": "https://ja.wikipedia.org/?curid=3941827",
                "title": "津田耕",
                "text": "〇〇は、日本の版画家。元日本宣伝美術会会員。"
            },
            {
                "datetime": "2025年06月16日 18時の問題",
                "url": "https://ja.wikipedia.org/?curid=889875",
                "title": "フサオマキザル",
                "text": "〇〇は、オマキザル科オマキザル属に分類されるサル。この項目は〇〇という種についてのものだが、別種C. flavius (C. flavius)、C. libidinosus (C. libidinosus)、C. nigritus (C. nigritus)、C. xanthosternos (C. xanthosternos) の知見を含んでいることがありうる。これは、従来これらの種が本稿の〇〇 (C. apella) の亜種として分類されてきたためである。新しく受容されている分類と従来の旧分類との対応については、亜種と分布の節で詳述する。"
            },
            {
                "datetime": "2025年06月16日 17時の問題",
                "url": "https://ja.wikipedia.org/?curid=4314193",
                "title": "Cinetorhynchus rigens",
                "text": "〇〇は、サラサエビ科アカモンサラサエビ属に分類されるエビの一種。英語名メカニカル・シュリンプ（mechanical shrimp）、アトランティック・ダンシング・シュリンプ（Atlantic dancing shrimp）、レッド・ナイト・シュリンプ（Red night shrimp）、レッド・コーラル・シュリンプ（Red coral shrimp）、スペイン語名カマロン・バイラドール（Camaròn bailador）、ポルトガル語名カマラオ・マリャード（Camarão malhado）、カマラオ・オルナメンタル（Camarão ornamental）、カマラオ・バイラリーノ（Camarão bailarino）。アカモンサラサエビ属の模式種。熱帯に位置する大西洋の沿岸に生息している。"
            },
            {
                "datetime": "2025年06月16日 16時の問題",
                "url": "https://ja.wikipedia.org/?curid=3054189",
                "title": "スタファン",
                "text": "〇〇は、H-[C≡(-CH2-)3≡C-]nHの分子構造を持つ炭化水素の有機化合物である。従って、化学式はC5nH6n+2となる。〇〇は、1988年に、Piotr KaszyńskiとJosef Michlによって、[1.1.1]プロペラン（C5H6またはC2(=CH2)3）の自発的な重合反応によって初めて得られた。軸となるプロペランのC-C結合は解離し、2つの軸の炭素と新しい結合を形成する。その結果生じる構造[-C≡(-CH2-)3≡C-]は堅固で、2つの炭素原子が3つのメタンジイル基で結合した構造を持つ。従って、構造単位は直鎖状になる。この特性から、〇〇のオリゴマーを用いてナノ構造体の作成が考えられ、ナノテクノロジーの分野においても興味を持たれているn個の単量体で構成される〇〇のオリゴマーを、[n]〇〇と呼ぶ。"
            },
            {
                "datetime": "2025年06月16日 15時の問題",
                "url": "https://ja.wikipedia.org/?curid=4566372",
                "title": "サミー・バディバンガ",
                "text": "〇〇は、コンゴの政治家。第31代コンゴ民主共和国首相。2018年のコンゴ民主共和国総選挙では、大統領候補として投票にも参加した。"
            },
            {
                "datetime": "2025年06月16日 14時の問題",
                "url": "https://ja.wikipedia.org/?curid=3349394",
                "title": "VfBシュトゥットガルトの選手一覧",
                "text": "〇〇は、ドイツのシュトゥットガルトに本拠地を置くVfBシュトゥットガルトに現在在籍しているまたは過去に在籍していた選手・監督の一覧である。"
            },
            {
                "datetime": "2025年06月16日 13時の問題",
                "url": "https://ja.wikipedia.org/?curid=2477495",
                "title": "酒井忠利 (海軍軍人)",
                "text": "〇〇は、日本の海軍軍人。出羽庄内藩主・酒井左衛門尉家の一門で、米津政明の次男、酒井忠発の養子（三男）。伯爵・酒井忠良の養大叔父、子爵・米津政賢の叔父にあたる。備中松山藩主で、子爵・板倉勝定（勝貞）、陸軍大将・西尾寿造は女婿。従四位勳三等功四級。最終階級は海軍少将。"
            },
            {
                "datetime": "2025年06月16日 12時の問題",
                "url": "https://ja.wikipedia.org/?curid=2475036",
                "title": "Gポテト",
                "text": "〇〇は、日本のガーラグループが運営していたオンラインゲームポータルサイト。国内でのサービス開始は2006年10月2日であり、元は株式会社ガーラによってサービスが運営されていたが、2008年7月1日よりガーラジャパンに運営が移管された。その後、2018年2月28日にサービス終了となった。2011年11月14日時点で、全世界での会員数は2066万人（ID）で、国内の会員数は69万人（ID）である。ただし、各国のサービスは独立している為、ある国で取得したgポテトIDは他国のgポテトサービスでは使用できない。gポテトにて提供されているゲームの特徴として、全て基本プレイ無料・ゲームアイテム販売型のゲームであることがあげられる。以下、特記なき場合は日本版のサービスについて述べる。"
            },
            {
                "datetime": "2025年06月16日 11時の問題",
                "url": "https://ja.wikipedia.org/?curid=214310",
                "title": "地域猫",
                "text": "〇〇は、「地域の理解と協力を得て、地域住民の認知と合意が得られている、特定の飼い主のいない外猫」を指す。〇〇活動（ちいきねこかつどう）とは、「不妊去勢手術を行ったり、新しい飼い主を探して飼い猫にしていくことで、将来的に飼い主のいない猫をなくしていくことを目的とした活動」であり、頭数抑制効果を得るには、地域の野良猫全体の 51%以上に不妊去勢手術を施す必要があるとされる。そのような活動により管理されている野良猫が〇〇と呼ばれることになる。管理実態によっては飼い主のいる猫、または飼い主のいない猫として判断される場合もある。本項では〇〇および〇〇活動について記す。"
            },
            {
                "datetime": "2025年06月16日 10時の問題",
                "url": "https://ja.wikipedia.org/?curid=3947306",
                "title": "アメフクラガエル",
                "text": "〇〇は、フクラガエル科のカエルである。"
            },
            {
                "datetime": "2025年06月16日 09時の問題",
                "url": "https://ja.wikipedia.org/?curid=600824",
                "title": "フレミングの左手の法則",
                "text": "〇〇は、ジョン・フレミングが考案した電磁気現象の記憶法で、磁場中の導体に電流が流れるときにその導体に力（ローレンツ力）が作用する現象において、磁場と電流と力の向きの関係を左手の指で示す方法である。"
            },
            {
                "datetime": "2025年06月16日 08時の問題",
                "url": "https://ja.wikipedia.org/?curid=2669204",
                "title": "Quarter Century Box",
                "text": "〇〇は、2012年10月25日に発売されたUNICORNのボックス・セット。同年12月19日発売のシングルリマスター・コレクション「Quarter Century Single Best」（クォーター・センチュリー・シングル・ベスト）、オールタイム・ライブベスト「Quarter Century Live Best」（クォーター・センチュリー・ライブ・ベスト）についても本項で記述する。"
            },
            {
                "datetime": "2025年06月16日 07時の問題",
                "url": "https://ja.wikipedia.org/?curid=2510225",
                "title": "小雪沢駅",
                "text": "〇〇は、かつて秋田県大館市雪沢字下谷地にあった同和鉱業（現・小坂製錬）小坂線（小坂鉄道）の駅（廃駅）である。762 mm軌間の軽便鉄道規格路線時代には、当駅にて電気機関車と蒸気機関車の付け替えを行っていた。"
            },
            {
                "datetime": "2025年06月16日 06時の問題",
                "url": "https://ja.wikipedia.org/?curid=4223429",
                "title": "岡野或男",
                "text": "〇〇は、長野県諏訪市出身の実業家。東洋バルヴ社長・旧ルネ・ラリック美術館の創設者（現在のSUWAガラスの里）・ホテル紅や社長・北澤美術館副理事長。"
            },
            {
                "datetime": "2025年06月16日 05時の問題",
                "url": "https://ja.wikipedia.org/?curid=496382",
                "title": "レノファ山口FC",
                "text": "〇〇は、日本の山口県全19市町をホームタウンとする、日本プロサッカーリーグ（Jリーグ）に加盟するプロサッカークラブ。"
            },
            {
                "datetime": "2025年06月16日 04時の問題",
                "url": "https://ja.wikipedia.org/?curid=1752400",
                "title": "ウォーソー (イリノイ州)",
                "text": "〇〇は、アメリカ合衆国のイリノイ州ハンコック郡にある市。人口は1,510人（2020年）。ミシシッピ川東岸にあり対岸はミズーリ州である。"
            },
            {
                "datetime": "2025年06月16日 03時の問題",
                "url": "https://ja.wikipedia.org/?curid=4073948",
                "title": "ダイハツ・シャレードソシアル",
                "text": "〇〇は、ダイハツ工業がかつて生産・販売していたセダン型普通乗用車である。"
            },
            {
                "datetime": "2025年06月16日 02時の問題",
                "url": "https://ja.wikipedia.org/?curid=779150",
                "title": "白い恐怖",
                "text": "〇〇は、1945年のアメリカ合衆国のサイコスリラー映画。監督はアルフレッド・ヒッチコック、出演はイングリッド・バーグマンとグレゴリー・ペックなど。原作はフランシス・ビーディングの1927年の小説『The House of Dr. Edwardes』。記憶喪失を題材にした作品で、主人公が垣間見る印象的な幻想シーンにはサルバドール・ダリが協力している。原題の『Spellbound』には「魔法にかかった」「魅了された」「うっとりした」などの意味がある。バーグマンの絶頂期の作品と言われ、美貌と演技力がともに発揮されている。"
            },
            {
                "datetime": "2025年06月16日 01時の問題",
                "url": "https://ja.wikipedia.org/?curid=444943",
                "title": "鬼剣舞",
                "text": "〇〇は、岩手県北上市周辺に伝わる伝統芸能である。地元では、剣舞を「けんべぇ」とも言う。北上・みちのく芸能まつりを初め、この地方の夏祭りなどで盛んに披露されるほか、小・中学校の運動会のアトラクションとしても演じられ、地元に根付いている。複数の踊り組団体がある（後述、〇〇伝承系統、〇〇伝承系図、参照）。1993年（平成5年）12月13日に代表的な北上市の岩崎〇〇と滑田〇〇の2団体・奥州市の朴ノ木沢念仏剣舞と川西大念佛剣舞の2団体が一括し、国の重要無形民俗文化財「〇〇」として指定された。"
            },
            {
                "datetime": "2025年06月16日 00時の問題",
                "url": "https://ja.wikipedia.org/?curid=3565075",
                "title": "ガブリエル・ポセンティ",
                "text": "〇〇は、イタリアのカトリック教会御受難会の修道者、聖人。修道名は「悲しみの聖母のガブリエル」（Gabriele dell'Addolorata）。"
            },
            {
                "datetime": "2025年06月15日 23時の問題",
                "url": "https://ja.wikipedia.org/?curid=1501707",
                "title": "ニューカッスル・ユナイテッドWFC",
                "text": "〇〇は、イングランド、ニューカッスルを本拠地とするサッカークラブチームである。2021-2022シーズンはFA女子ナショナルリーグ・ディヴィジョン・ワン・ノース（3部相当）に所属。"
            },
            {
                "datetime": "2025年06月15日 22時の問題",
                "url": "https://ja.wikipedia.org/?curid=2944797",
                "title": "トゥザワールド",
                "text": "〇〇は、日本の競走馬である。馬名の意味は世界へ向かって。母のトゥザヴィクトリーより連想。主な勝ち鞍は2014年の弥生賞。全兄に日経賞など重賞5勝、有馬記念3着2度の実績を持つ同馬主、同厩舎のトゥザグローリーがおり、同馬も2014年の有馬記念で9番人気ながら2着に好走している。"
            },
            {
                "datetime": "2025年06月15日 21時の問題",
                "url": "https://ja.wikipedia.org/?curid=3981022",
                "title": "古代の智慧のマスター",
                "text": "〇〇は、もともと神学者 ヘレナ・P・ブラヴァツキー、ヘンリー・S・オルコット、アルフレッド・パーシー・シンネット、その他の神智学者が接触したと信じられている悟りを開いた存在である。これらの人物は、その生涯の間に世界のさまざまな場所で、そのようなマスターと出会ったと主張した。アデプト、マハトマ、または単にマスター、大師と呼ばれることもある。 マスターの概念を最初に西洋に紹介したのは、ヘレナ・P・ブラヴァツキーであると言われる。当初、彼らと個人的に会話を交わせるのは彼女だけだったが、数年後には、こうしたマスターのうち、クートフーミ（KH）とMモリヤ （M.）が神学者のアルフレッド・パーシー・シネットと、鳥類学者のアラン・オクタヴィアン・ヒュームの2人との通信に同意したと信じられている。このコミュニケーションは1880年から1885年まで行われ、その間にマハトマの存在と目的は公になった。マスターから「受け取った」と言われるオリジナルの手紙は、現在ロンドンの大英図書館に保管されており、『マハトマ書簡』として出版されている。"
            },
            {
                "datetime": "2025年06月15日 20時の問題",
                "url": "https://ja.wikipedia.org/?curid=1625310",
                "title": "ドボチョン一家の幽霊旅行",
                "text": "〇〇は、1971年から1972年までアメリカ合衆国のABCで放送されていたハンナ・バーベラ・プロダクション制作のテレビアニメである。"
            },
            {
                "datetime": "2025年06月15日 19時の問題",
                "url": "https://ja.wikipedia.org/?curid=4740927",
                "title": "朝長正軌",
                "text": "〇〇は、日本の経営者。JCB社長を務めた。長崎県出身。"
            },
            {
                "datetime": "2025年06月15日 18時の問題",
                "url": "https://ja.wikipedia.org/?curid=2365545",
                "title": "アン・ドゥー",
                "text": "〇〇は、岡山県岡山市に本社を置くアパレル（衣料品）の製造・販売を展開する会社（SPA）である。"
            }
        ]
    }
}