{
    "data": {
        "wiki": [
            {
                "datetime": "2024年09月09日 00時の問題",
                "url": "https://ja.wikipedia.org/?curid=1835039",
                "title": "モラロジー道徳教育財団",
                "text": "〇〇は、千葉県柏市光ヶ丘2-1-1に本部を置く公益財団法人。廣池千九郎が説いた「道徳科学」（moral+-logy）を基にして1926年に設立された修養・道徳団体「道徳科学研究所」を前身とする。教育再生、道徳教育による「日本人の心の再生」を主張し、その出発点を家庭に置く。2021年に「モラロジー研究所」から現在の名称に変更された。"
            },
            {
                "datetime": "2024年09月08日 23時の問題",
                "url": "https://ja.wikipedia.org/?curid=210134",
                "title": "中央競馬の冠競走一覧",
                "text": "〇〇は、中央競馬で行われる新聞社、放送局などのスポンサーの社名を冠した競走の一覧である。全国一般紙・全国スポーツ紙・農林水産大臣については関東主場→関西主場→第3場（北から）の順番で掲載している。また他のスポンサー企業についても関東→関西→第3場の地域（北から）での順番で掲載している。"
            },
            {
                "datetime": "2024年09月08日 22時の問題",
                "url": "https://ja.wikipedia.org/?curid=32904",
                "title": "エルサルバドル",
                "text": "〇〇は、中央アメリカ中部に位置する、ラテンアメリカの共和制国家である。北西にグアテマラ、北と東にホンジュラスと国境を接しており、南と西は太平洋に面している。中央アメリカ5か国のうち唯一、カリブ海に面していない。首都はサンサルバドル。カリブ海の島国を除く米州大陸部全体で最小の国家であるが、歴史的に国土の開発が進んでいたこともあり、人口密度では米州最高である。"
            },
            {
                "datetime": "2024年09月08日 21時の問題",
                "url": "https://ja.wikipedia.org/?curid=1002794",
                "title": "ショーン・ディロン",
                "text": "〇〇は、ジャック・ヒギンズの小説に登場する架空の人物。〇〇・シリーズと称される一連のシリーズの主人公。"
            },
            {
                "datetime": "2024年09月08日 20時の問題",
                "url": "https://ja.wikipedia.org/?curid=2390814",
                "title": "幸美AMP",
                "text": "〇〇は、シンガーソングライターのVo&Gtゆきみと、Dr&Cho直輝のメンバーに加え、サポートベーシストにを迎えた日本の3ピースrockバンド。"
            },
            {
                "datetime": "2024年09月08日 19時の問題",
                "url": "https://ja.wikipedia.org/?curid=4257249",
                "title": "茉莉花官吏伝",
                "text": "〇〇は、石田リンネによる日本のライトノベル。ビーズログ文庫 (KAKOKAWA) より2017年7月より刊行されている。『月刊プリンセス』（秋田書店）にて2018年9月号から高瀬わかによるコミカライズが連載されている。2024年5月時点でシリーズ累計部数は173万部を記録している。 また、莉杏と暁月をメインとしたスピンオフ『十三歳の誕生日、皇后になりました。』 がビーズログ文庫に（同）て2018年10月から刊行されている。このスピンオフも『月刊プリンセス』（同）にて2020年3月から青井みとによるコミカライズが連載されている。"
            },
            {
                "datetime": "2024年09月08日 18時の問題",
                "url": "https://ja.wikipedia.org/?curid=2492980",
                "title": "マルクス・アウレリウス・クレアンデル",
                "text": "〇〇は、ローマ帝国の政治家。一般にクレアンデル（Cleander）と呼ばれ、第17代ローマ皇帝ルキウス・アウレリウス・コンモドゥス・アントニヌスの侍従長（執事）として立身を果たし、皇帝からの信頼を武器に汚職政治を行ったと言われている。一時は近衛隊長の地位まで手にしたが、やがてコンモドゥス帝に処刑された。その存在は同時代の歴史家・元老院議員であるカッシウス・ディオも言及している。"
            },
            {
                "datetime": "2024年09月08日 17時の問題",
                "url": "https://ja.wikipedia.org/?curid=84961",
                "title": "泉屋博古館",
                "text": "〇〇は、京都市左京区鹿ヶ谷（ししがたに）にある、東洋美術が中心の美術館。住友家寄贈の中国古代青銅器を中心に保存公開、運営は公益財団法人〇〇。東京都港区六本木に分館があり、2021年4月より館名を「〇〇東京」に変更した。"
            },
            {
                "datetime": "2024年09月08日 16時の問題",
                "url": "https://ja.wikipedia.org/?curid=1762065",
                "title": "渋川尹繁",
                "text": "〇〇は、室町時代後期から戦国時代にかけての武将・九州探題。"
            },
            {
                "datetime": "2024年09月08日 15時の問題",
                "url": "https://ja.wikipedia.org/?curid=3651153",
                "title": "棚橋訓",
                "text": "〇〇は、日本の文化人類学者。お茶の水女子大学教授。"
            },
            {
                "datetime": "2024年09月08日 14時の問題",
                "url": "https://ja.wikipedia.org/?curid=2525655",
                "title": "犬山紙子",
                "text": "〇〇は、日本のコラムニスト、エッセイスト、ラジオパーソナリティ。大阪生まれで、幼少時代を大阪府と兵庫県で過ごし、中学時に宮城県へ移住する。仙台市の出版社で編集者として勤務するが介護離職し、その後マガジンハウスからブログ本「負け美女」を出版する。作家デビュー後は雑誌、ラジオなどのメディアなどに出演し、TVでコメンテーターとしても活動している。"
            },
            {
                "datetime": "2024年09月08日 13時の問題",
                "url": "https://ja.wikipedia.org/?curid=2908209",
                "title": "蒼波純",
                "text": "〇〇は、日本の女優、女性アイドル、モデル。旧芸名は青波純。本名は青沼純。宮城県出身。"
            },
            {
                "datetime": "2024年09月08日 12時の問題",
                "url": "https://ja.wikipedia.org/?curid=3950592",
                "title": "井上忠浩",
                "text": "〇〇は、日本の実業家であり、マーリン・エンターテイメンツ・ジャパン株式会社の代表取締役。2018年8月1日より株式会社クラブメッドにて「マーケティング・オムニチャネル戦略事業本部」取締役を務める。研究者としての顔も持ち、2017年に大阪大学大学院経済学研究科より人工知能学会にて教授の松村真宏と共に仕掛学のセッションにおいて仕掛けのWearOUT効果（飽きられる効果）、およびWearIN効果（興味をもってもらう効果）に関する実験結果について報告している。"
            },
            {
                "datetime": "2024年09月08日 11時の問題",
                "url": "https://ja.wikipedia.org/?curid=3265349",
                "title": "花畑小学校",
                "text": "〇〇は、日本の公立小学校。足立区立〇〇 - 東京都福岡市立〇〇 - 福岡県"
            },
            {
                "datetime": "2024年09月08日 10時の問題",
                "url": "https://ja.wikipedia.org/?curid=2824429",
                "title": "山岸紀郎",
                "text": "〇〇は、日本の元バレーボール審判員、日本バレーボール協会専務理事、初代Vリーグ機構代表理事（会長）。"
            },
            {
                "datetime": "2024年09月08日 08時の問題",
                "url": "https://ja.wikipedia.org/?curid=278892",
                "title": "東京ミッドナイトエクスプレス京都号",
                "text": "〇〇は、東京都と京都府京都市・大阪府枚方市を結ぶ夜行高速バス路線である。本項では、かつて運行されていた「東京ミッドナイトエクスプレス宇治号」についても記載する。"
            },
            {
                "datetime": "2024年09月08日 07時の問題",
                "url": "https://ja.wikipedia.org/?curid=4456063",
                "title": "ボルダー・メディア",
                "text": "〇〇は、アイルランドのアニメーションスタジオ。オーストラリアのメディア会社プリンセスピクチヤーズの子会社。2000年にロバート・カレンによって設立。2022年11月1日、ハズブロは〇〇をオーストラリアのメディア会社プリンセスピクチヤーズに売却し、大人向けアニメシリーズの『Smiling Friends』、『YOLO: Crystal Fantasy』、『Koala Man』をベントボックスエンターテインメントの合弁会社であるプリンセスベントで制作した。"
            },
            {
                "datetime": "2024年09月08日 06時の問題",
                "url": "https://ja.wikipedia.org/?curid=4914047",
                "title": "町田市立山崎小学校",
                "text": "〇〇は、東京都町田市忠生二丁目にある公立小学校。校内敷地内に、山崎学童保育クラブの建物がある。2023年4月現在の学級数は12学級、全校児童338人である。"
            },
            {
                "datetime": "2024年09月08日 05時の問題",
                "url": "https://ja.wikipedia.org/?curid=897142",
                "title": "佐々木瑶子",
                "text": "〇〇は、日本の女優、声優である。茨城県出身。以前は東京都俳優生活協同組合（俳協）に所属していた。佐々木 庸子から改名した。身長160cm。体重47kg。"
            },
            {
                "datetime": "2024年09月08日 04時の問題",
                "url": "https://ja.wikipedia.org/?curid=1437605",
                "title": "スー・ウィリアムズ",
                "text": "〇〇は、アメリカ合衆国の男性向雑誌PLAYBOY誌・1965年4月号のプレイメイト、女優。彼女の中央見開き折込ページ（センターフォールド）は、エド・デロング (Ed DeLong) とウィリアム・V・フィッゲ (William V.  Figge) によって撮影された。"
            },
            {
                "datetime": "2024年09月08日 03時の問題",
                "url": "https://ja.wikipedia.org/?curid=1179385",
                "title": "春の歌 (映画)",
                "text": "〇〇は、1945年（昭和20年）に、日本で2番目に製作されたカラー映画。空襲で田舎に疎開した小学生と教師とのふれ合いを描いた作品である。"
            },
            {
                "datetime": "2024年09月08日 02時の問題",
                "url": "https://ja.wikipedia.org/?curid=3695760",
                "title": "薄葉ヶ原の戦い",
                "text": "〇〇は、天正13年（1585年）に下野国で行われた合戦である。"
            },
            {
                "datetime": "2024年09月08日 01時の問題",
                "url": "https://ja.wikipedia.org/?curid=1014426",
                "title": "福井県道114号吉野福井線",
                "text": "〇〇は、福井県福井市と吉田郡永平寺町を結ぶ県道（主要地方道）。"
            },
            {
                "datetime": "2024年09月08日 00時の問題",
                "url": "https://ja.wikipedia.org/?curid=3149091",
                "title": "ブラインドカーボンコピー",
                "text": "〇〇は、電子メールの機能の一種で、複数の利用者あてに電子メールを同時送信する際、受取人以外の送信先メールアドレスを伏せて送信することである。企業が顧客に一斉送信するような場合にも用いられるが、勘違いや操作ミスなどから誤ってBccでなくCcしてしまう場合があり、使用には相当な注意が必要である。また、複数の異なる動作例が、RFC733にて言及されている。"
            },
            {
                "datetime": "2024年09月07日 23時の問題",
                "url": "https://ja.wikipedia.org/?curid=3565645",
                "title": "オーロラの救世主 (曲)",
                "text": "〇〇は、エレクトリック・ライト・オーケストラが1976年に発表した楽曲。アルバム「オーロラの救世主」に収録されている。"
            },
            {
                "datetime": "2024年09月07日 22時の問題",
                "url": "https://ja.wikipedia.org/?curid=3889388",
                "title": "劉荊",
                "text": "〇〇は、後漢の皇族。広陵思王。"
            },
            {
                "datetime": "2024年09月07日 21時の問題",
                "url": "https://ja.wikipedia.org/?curid=4778928",
                "title": "朴鎮洪",
                "text": "〇〇は、朝鮮の女性の独立運動家、労働運動家。"
            },
            {
                "datetime": "2024年09月07日 20時の問題",
                "url": "https://ja.wikipedia.org/?curid=1133200",
                "title": "アンカレッジ交響楽団",
                "text": "〇〇は、アメリカ合衆国アラスカ州アンカレッジに拠点を置くセミプロフェッショナルのオーケストラ。1946年に演奏団体を欲する音楽家達の団体の手によって創設された。第1回目のプログラムはアンカレジ・リトル・シアターとの共同でチャールズ・ディッケンズのクリスマス・キャロルを上演した。最初期には17人の楽員で構成されていた〇〇も、ピーター・バーチを指揮者に迎えた1950年代を通して、32人の楽員からなるオーケストラに成長した。また、ノーススロープ油田の開発によりアンカレッジ市の都市開発は進み、エルメンドルフ空軍基地の軍駐留に伴って〇〇はセミプロフェッショナルの音楽団体に成長した。今日、〇〇は寄付金と役員会、オーディションを経た80人の音楽家を誇りにしている。2001年、「卓越した芸術団体のための芸術市長賞（Mayor's Arts Award for an Outstanding Arts Organization）」及び「卓越した芸術団体のための芸術州知事賞（Governor's Arts Award for an Outstanding Arts Organization）」を受賞した。〇〇は、アンカレッジのダウンタウンに位置するアラスカ・センター・フォー・ザ・パフォーミング・アーツで演奏している。"
            },
            {
                "datetime": "2024年09月07日 19時の問題",
                "url": "https://ja.wikipedia.org/?curid=403977",
                "title": "報徳思想",
                "text": "〇〇は、二宮尊徳が説き広めた経済思想、経済学説。"
            },
            {
                "datetime": "2024年09月07日 18時の問題",
                "url": "https://ja.wikipedia.org/?curid=236602",
                "title": "エレクトロニックフラッシュ",
                "text": "〇〇は、主に写真撮影の際に使われる発光装置。発明以前に広く使われていたフラッシュバルブ（閃光電球）との区別のためこの名称となったが、その後フラッシュバルブが使用されなくなったため単に「フラッシュ」と略称されている場合が多い。日本ではストロボとも呼ばれる。英語で\"strobe\"は、ストロボスコープを意味する\"stroboscope\"やそのための照明を意味する\"strobe light\"の短縮形で、普通名称である。アメリカ合衆国では、ストロボリサーチ社（Strobo Research Co. ）によって1950年に\"Strob\"（語尾に\"O\"も\"E\"も付かない）が商標登録されているが、1991年に権利期間が終了している。なお、商標登録は国毎に行われるものであり、商標登録されていない国では商標の使用は制限されない。日本においては、2013年（平成25年）現在では、〇〇について「ストロボ」、「Strob」、「Strobe」のいずれも商標登録されていない。メーカーによっては「スピードライト」などと呼称している場合がある。英語圏では\"Flash light\"、または単に\"Flash\"もしくは\"Strobe light\"または単に\"Strobe\"と呼ぶことが多い。単発を\"Flash light\"と呼び、点滅を繰り返す場合を\"Strobe light\"と呼んで使い分けることもある。ただしアメリカなどでの\"Flashlight\"は、一般に懐中電灯のことを指す。なお、フラッシュを使用すると被写体によっては撮影結果に大きな影響を及ぼすため、調査・研究資料としての記録写真には不向きなケースもある。右の魚卵の画像を参照されたい。上段がフラッシュを使用した画像であるが、使わない画像（現物を肉眼で見た状態に近い）と比べて色合いや質感の印象が大きく異なってしまっている。"
            },
            {
                "datetime": "2024年09月07日 17時の問題",
                "url": "https://ja.wikipedia.org/?curid=2399485",
                "title": "The FEAR",
                "text": "〇〇は、2001年7月26日にエニックス（現スクウェア・エニックス）より発売されたPlayStation 2用ホラーアドベンチャーゲーム。齊藤陽介プロデュースの全編実写を特徴とする「シネマアクティブ」シリーズの第3弾である。"
            },
            {
                "datetime": "2024年09月07日 16時の問題",
                "url": "https://ja.wikipedia.org/?curid=3377265",
                "title": "クリジナー鍾乳洞",
                "text": "〇〇は、スロベニアにある鍾乳洞。ブロスコーポリシァ町から約1.5キロメートルの場所に洞窟の入口がある。カルスト地形で、ロスコー野原とシェルークニスコー野原とブロスコー台地の間の8,273メートルにわたる長い洞窟に鍾乳石が多く見られることで有名。イェゼーラスコ道とピーサーニ道に22、ブラッタ道も含めると40以上にのぼる緑玉色の水をたたえた地底湖があり、島もある。壁書は16世紀に描かれたと見られている。また、もっとも古い文献の記録としては、1832年に立ち入ったとされている。洞窟は近くのセント・クリジャ教会の名をとって名付けられた。洞窟の生態系としては、生物多様性において、4番目に有名である。2000年までには、45種類の洞窟生物が発見された。東ヨーロッパの地域で、ドウクツ熊の骨が発見された宝庫の一つであり、熊の骨のほか、洞窟の入口付近では青銅器時代の陶器や石も発見された。"
            },
            {
                "datetime": "2024年09月07日 15時の問題",
                "url": "https://ja.wikipedia.org/?curid=1054144",
                "title": "冷血",
                "text": "〇〇は、トルーマン・カポーティが1965年に発表した小説。"
            },
            {
                "datetime": "2024年09月07日 14時の問題",
                "url": "https://ja.wikipedia.org/?curid=2517941",
                "title": "北原耕也",
                "text": "〇〇は、日本の作家。宮城県牡鹿郡蛇田村（現石巻市）出身。仙台市在住。大学を中退して演劇の世界に身を投ずる。その間、十指に余る職業を経験。この体験から、長く労働組合運動に関わる。のちに一線を退き、作家。小説のほか、ノンフィクション、文芸評論など幅広い分野で執筆活動をおこなっている。日本民主主義文学会会員。2011年3月11日、仙台市若林区にいて東日本大震災に遭遇。その体験と大勢の児童・教師が犠牲になった郷里石巻市の市立大川小学校の惨事から、管理下にあった児童・生徒全員が助かった釜石市への取材を思い立ち、ルポルタージュ『津波の町に生きる』を執筆、出版する。"
            },
            {
                "datetime": "2024年09月07日 13時の問題",
                "url": "https://ja.wikipedia.org/?curid=2703286",
                "title": "デイヴ・ホランド",
                "text": "〇〇は、イングランド出身のジャズ・ベーシスト。"
            },
            {
                "datetime": "2024年09月07日 12時の問題",
                "url": "https://ja.wikipedia.org/?curid=4713403",
                "title": "レッド・ロビンス",
                "text": "〇〇は、アメリカ合衆国の元プロバスケットボール選手。身長203cm、体重86kg。ポジションはセンター及びパワーフォワード。ABAでオールスターに4度選出された。"
            },
            {
                "datetime": "2024年09月07日 11時の問題",
                "url": "https://ja.wikipedia.org/?curid=3706774",
                "title": "ミオドラグ・ライコビッチ",
                "text": "〇〇は、セルビア共和国のプロバスケットボール指導者。ユーゴスラビアベオグラード出身。役職はヘッドコーチ。"
            },
            {
                "datetime": "2024年09月07日 10時の問題",
                "url": "https://ja.wikipedia.org/?curid=3975086",
                "title": "ヴァロンゴ埠頭の考古遺跡",
                "text": "〇〇は、リオ・デ・ジャネイロの中心地に位置するバラン・デ・テフェー通り（Avenida Barão de Tefé）沿いの公園内にある19世紀の港湾の遺跡からなるブラジルの世界遺産である。"
            },
            {
                "datetime": "2024年09月07日 08時の問題",
                "url": "https://ja.wikipedia.org/?curid=3739609",
                "title": "大辻駅",
                "text": "〇〇は、かつて福岡県中間市にあった、鉄道院筑豊本線の貨物駅（廃駅）である。貨物支線の廃線に伴い、1911年（明治44年）9月1日に廃駅となった。"
            },
            {
                "datetime": "2024年09月07日 07時の問題",
                "url": "https://ja.wikipedia.org/?curid=128060",
                "title": "阪急2000系電車",
                "text": "〇〇は、阪急電鉄（以下「阪急」）が1960年から神戸線・宝塚線（神宝線）用として導入した通勤形電車である。本項では、本系列の宝塚線用の低速型である2100系電車、直流600V・1500V複電圧対応型である2021系電車（電装解除後は2071系）についても記述する。能勢電鉄がこれら3形式を阪急から譲受した系列は、能勢電鉄1500系電車と能勢電鉄1700系電車の各記事で解説する。"
            }
        ]
    }
}