{
    "data": {
        "wiki": [
            {
                "datetime": "2025年04月04日 10時の問題",
                "url": "https://ja.wikipedia.org/?curid=189842",
                "title": "長野県上田高等学校",
                "text": "〇〇は、長野県上田市大手一丁目にある公立高校である。男女共学で、全日制普通科と定時制普通科を設置している。全日制では、国立大学を中心に難関大に合格者を輩出している。"
            },
            {
                "datetime": "2025年04月04日 09時の問題",
                "url": "https://ja.wikipedia.org/?curid=2222146",
                "title": "スニッター・リーティクン",
                "text": "〇〇は、タイの歌手。通称：ボー（โบ、Beau）。タイ人の母とアフガニスタン人の父を持つ。1993年、18歳でタイ音楽会社大手グラムミーからデビューしている。"
            },
            {
                "datetime": "2025年04月04日 08時の問題",
                "url": "https://ja.wikipedia.org/?curid=3960963",
                "title": "奥原正明",
                "text": "〇〇は、日本の農林官僚。農林水産省消費・安全局長、経営局長などを歴任し、2016年6月から2018年7月まで農林水産事務次官を務めた。2019年7月から株式会社オプティム経営諮問委員会エグゼクテイブアドバイザー、公益社団法人日本農業法人協会顧問。"
            },
            {
                "datetime": "2025年04月04日 07時の問題",
                "url": "https://ja.wikipedia.org/?curid=4252442",
                "title": "山田優弥",
                "text": "〇〇は、日本の俳優。青森県弘前市出身。プロジェクト・パーン所属。"
            },
            {
                "datetime": "2025年04月04日 06時の問題",
                "url": "https://ja.wikipedia.org/?curid=186723",
                "title": "競輪場前停留場",
                "text": "〇〇は、愛知県豊橋市東田町にある豊橋鉄道東田本線の停留場（電停）である。停留場番号は11。豊橋競輪場への最寄駅であるが、停留所から競輪場までは約500 mほどあり、競輪開催時には豊橋駅前から無料のシャトルバスが運行されるため、競輪場へ行く客はあまり利用していない。留置線があるため始発、終着の電車が朝夕に何本か存在する。"
            },
            {
                "datetime": "2025年04月04日 05時の問題",
                "url": "https://ja.wikipedia.org/?curid=274278",
                "title": "鳥取県道293号鳥取郡家線",
                "text": "〇〇は、鳥取県鳥取市から八頭郡八頭町に至る一般県道である。"
            },
            {
                "datetime": "2025年04月04日 04時の問題",
                "url": "https://ja.wikipedia.org/?curid=3532900",
                "title": "MAGiCAL MYSTERY TOUR (マジカル・パンチラインのアルバム)",
                "text": "〇〇は、日本の女性アイドルグループ「マジカル・パンチライン」が、2016年12月21日にポニーキャニオンからリリースした、2枚目のミニアルバム。"
            },
            {
                "datetime": "2025年04月04日 03時の問題",
                "url": "https://ja.wikipedia.org/?curid=2441338",
                "title": "タイニー・テンパー",
                "text": "〇〇は、イギリスのラッパーである。本名パトリック・ジュニアー・チュクエメカ・オコグ (Patrick Junior Chukwuemeka Okogwu)。2005年よりミックステープを出し始め、2009年『パス・アウト』でメジャーデビュー。ヒップホップにダブ・ステップや、ソウルやエレクトロニカの要素を巧みに織り交ぜたオリジナリティの高い楽曲が持ち味。"
            },
            {
                "datetime": "2025年04月04日 02時の問題",
                "url": "https://ja.wikipedia.org/?curid=3825125",
                "title": "リンゴ村から",
                "text": "〇〇は、1956年にリリースされた三橋美智也のシングル。"
            },
            {
                "datetime": "2025年04月04日 01時の問題",
                "url": "https://ja.wikipedia.org/?curid=1319296",
                "title": "熊本県道213号内牧坂梨線",
                "text": "〇〇は、熊本県阿蘇市を通る一般県道である。"
            },
            {
                "datetime": "2025年04月04日 00時の問題",
                "url": "https://ja.wikipedia.org/?curid=1515652",
                "title": "Enlightened Sound Daemon",
                "text": "〇〇は、EnlightenmentおよびGNOMEのサウンドサーバである。ESD は実行中の各種プログラムの出力する音をミキシングして、サウンドカードへのストリームを出力する。また、ネットワーク透過なサウンド管理もでき、ローカルなESD対応アプリケーションの発した音をESDサーバの動作するリモートのコンピュータで出力させることができる。ESD に対応するにはアプリケーション側にコードを追加しなければならず、ESD は通常のサウンド関連ハードウェアのAPIをエミュレートしていない。しかし最も初期のサウンドサーバとして登場から10年以上が経過しており、多くのUNIXアプリケーションがESDをサポートしている。ESDはGNOMEプロジェクトの一部として保守されている。代替サウンドサーバとして、JACK Audio Connection Kit （ネットワーク透過性はない）、aRtsd、NAS、PulseAudio などがある。"
            },
            {
                "datetime": "2025年04月03日 23時の問題",
                "url": "https://ja.wikipedia.org/?curid=3700636",
                "title": "ツルカノコソウ",
                "text": "〇〇は、スイカズラ科カノコソウ属に分類される多年草の1種。種小名（flaccidissima）は、「最も軟弱な」を意味する。和名の「ツル」は、つる枝をのばして繁殖する特徴に由来する。別名が「ヤマカノコソウ」。中国名が「柔垂纈草」。"
            },
            {
                "datetime": "2025年04月03日 22時の問題",
                "url": "https://ja.wikipedia.org/?curid=743080",
                "title": "村上ショージ",
                "text": "〇〇は、日本のお笑いタレント。本名は村上 昭二（むらかみ しょうじ）。愛媛県今治市出身。吉本興業東京所属。血液型B型、身長164cm。すべり芸を得意とする。村上ジョージは誤記。"
            },
            {
                "datetime": "2025年04月03日 21時の問題",
                "url": "https://ja.wikipedia.org/?curid=506869",
                "title": "ダグ・ファーナス",
                "text": "〇〇は、アメリカ合衆国のプロレスラー。オクラホマ州マイアミ出身。"
            },
            {
                "datetime": "2025年04月03日 20時の問題",
                "url": "https://ja.wikipedia.org/?curid=3418623",
                "title": "星野靖之助",
                "text": "〇〇は、日本の実業家、政治家。衆議院議員。"
            },
            {
                "datetime": "2025年04月03日 19時の問題",
                "url": "https://ja.wikipedia.org/?curid=2671402",
                "title": "アル・フジャイラ・スタジアム",
                "text": "〇〇は、アラブ首長国連邦のフジャイラにある多目的スタジアムである。"
            },
            {
                "datetime": "2025年04月03日 18時の問題",
                "url": "https://ja.wikipedia.org/?curid=1498846",
                "title": "関東自動車小山営業所",
                "text": "〇〇は、栃木県小山市神鳥谷（ひととのや）にある、関東自動車の営業所である。所属車輌のナンバープレートは、かつては「栃木」ナンバーであったが、現在は「とちぎ」に統一されている。2022年（令和4年）11月30日付で廃止された石橋営業所は、翌12月1日より当営業所石橋車庫に改組された。"
            },
            {
                "datetime": "2025年04月03日 17時の問題",
                "url": "https://ja.wikipedia.org/?curid=5008430",
                "title": "青山善敬",
                "text": "〇〇は、日本の地方公務員。兵庫県環境担当部長、同会計管理者、同人事委員会委員長、兵庫県公館長を歴任。瑞宝小綬章受章。"
            },
            {
                "datetime": "2025年04月03日 16時の問題",
                "url": "https://ja.wikipedia.org/?curid=4732587",
                "title": "オサム・ジェームス・中川",
                "text": "〇〇は、日系アメリカ人の写真家。中川はグッゲンハイム・フェローシップを受賞し、相模原市などから表彰されている。メトロポリタン美術館、東京都写真美術館、ヒューストン美術館、佐喜真美術館などで国際的な展覧会を開催。中川の作品は、現代写真美術館やジョージ・イーストマン美術館など、これらの美術館やその他の美術館のパブリックコレクションに属している。中川はインディアナ大学の写真学科の教授で、インディアナ州ブルーミントンに住み、活動している。"
            },
            {
                "datetime": "2025年04月03日 15時の問題",
                "url": "https://ja.wikipedia.org/?curid=3366473",
                "title": "さんふらわあ くろしお",
                "text": "〇〇は、ブルーハイウェイラインが運航したフェリー。"
            },
            {
                "datetime": "2025年04月03日 14時の問題",
                "url": "https://ja.wikipedia.org/?curid=1625",
                "title": "カメラ",
                "text": "〇〇は、写真や映像を撮影するための光学的な機械や装置。写真機（しゃしんき、寫眞機）ともいう。"
            },
            {
                "datetime": "2025年04月03日 13時の問題",
                "url": "https://ja.wikipedia.org/?curid=2136386",
                "title": "山口四郎",
                "text": "〇〇は、ドイツ文学者、翻訳家。中央大学名誉教授。1976年に第49回オール読物新人賞を受賞した〇〇は別人。"
            },
            {
                "datetime": "2025年04月03日 12時の問題",
                "url": "https://ja.wikipedia.org/?curid=180384",
                "title": "山田卓生",
                "text": "〇〇は、日本の法学者。専門は民法・法社会学。横浜国立大学名誉教授。弁護士。来栖三郎門下。"
            },
            {
                "datetime": "2025年04月03日 11時の問題",
                "url": "https://ja.wikipedia.org/?curid=1404767",
                "title": "Series/1",
                "text": "〇〇は、IBMが1976年にリリースした16ビットのミニコンピュータである。〇〇は1980年代後半には販売停止となった。"
            },
            {
                "datetime": "2025年04月03日 10時の問題",
                "url": "https://ja.wikipedia.org/?curid=612444",
                "title": "スコットランド人",
                "text": "〇〇は、スコットランド国民、またはスコットランドを父祖の土地とする民族のこと。単にスコッツ（Scots）ともいう。歴史的に彼らはピクト人とゲール人の融合から生まれ、南を接していたブリトン人を組み込むだけでなく、アングロ・サクソン人やノース人のような侵入してきたゲルマン系の諸族を取り込んでいった。現代的な用法では、〇〇またはスコッツは、言語、文化、家族の先祖または遺伝的起源がスコットランド内にある者を指すため使われる。ラテン語のScottiは元々5世紀に特定に使用された名称で、アイルランドに住むゴイデリック人を指していた。しかし時には古めかしく軽蔑的な意味合いから、Scotchという名称も〇〇を指して使われる。しかしこの名称は現在では主としてスコットランドの外でしか用いられていない。スコットランド国外の多くの国々にも、スコットランド系の人々がいる。ハイランド・クリアランス (Highland Clearances) やローランド・クリアランスの影響によるものや、大英帝国にスコットランドが参加したことによる移民、そして後期には産業の衰退と失業を理由として、世界中にスコットランド系の人々が見られるのである。〇〇の大集団は、南北アメリカ大陸、オーストラリア、ニュージーランドなど新大陸に移住した。カナダでは高い割合で〇〇の存在感がある。アメリカ合衆国についでカナダでは、〇〇を先祖に持つ人々が2番目に大きな人口を持っている。彼らは自らのスコットランドの言語と文化を引き継いでいる。スコットランドはその歴史の中で、異なる期間に人の移住や定住を経験している。ダルリアダ王国のゲール人、ピクト人、そしてブリトン人たちは、中世ヨーロッパの民族の多くと同じく独自の起源神話を持っていた。アングル人やサクソン人といったゲルマン民族は7世紀初頭に到来し、一方でノース人が8世紀以降スコットランドの多くの地域に定住した。デイヴィッド1世時代にあたる中世最盛期、フランス、イングランド、ネーデルラントからの移住者がいた。多くの有名なスコットランドの家名、ブルース家、ベイオール家、マレー家、ステュアート家はこの時代にスコットランドに到来した。現在のスコットランドは、グレートブリテン及び北アイルランド連合王国（イギリス）を構成する国（イギリスのカントリー）の1つであり、スコットランドに住む人々の大半は国籍法において連合王国市民である。"
            },
            {
                "datetime": "2025年04月03日 09時の問題",
                "url": "https://ja.wikipedia.org/?curid=1987204",
                "title": "上林貞治郎",
                "text": "〇〇は、日本の経済学者。半世紀を超える大学での教育活動や多くの著書を通じ、一貫して科学的社会主義の立場を貫徹し、学生や労働者に大きな影響を与えた。経済学博士。"
            },
            {
                "datetime": "2025年04月03日 08時の問題",
                "url": "https://ja.wikipedia.org/?curid=3984879",
                "title": "ウィリアム・マッコーイ",
                "text": "〇〇は、アメリカ合衆国の音響技術者である。アカデミー賞録音賞に5度ノミネートされ、1978年の『ディア・ハンター』で受賞した。"
            },
            {
                "datetime": "2025年04月03日 07時の問題",
                "url": "https://ja.wikipedia.org/?curid=3997634",
                "title": "スターニボリ",
                "text": "〇〇は、デンマークのエーレスンド海峡のヴェン島にある、ティコ・ブラーエの運営する地下天文観測施設であり、彼の住居兼観測所のウラニボリに隣接している。1581年頃に建設され、ティコは「私の目的の1つは、いくつかの重要な観測機器を風による振動に晒されないようにし、使いやすくすること、もう1つは、複数の共同研究者が同時に観測する時に動線を分けることである」と語った。彼はこの施設を「星の城」という意味の〇〇と名付けた。観測所の地下部分は、1950年代に発掘調査が行われ、元々構造があった場所に屋根がかけられ、公衆向けのマルチメディアショーを提供している。"
            },
            {
                "datetime": "2025年04月03日 06時の問題",
                "url": "https://ja.wikipedia.org/?curid=1682636",
                "title": "みねぐも (護衛艦)",
                "text": "〇〇は、海上自衛隊の護衛艦。みねぐも型護衛艦の1番艦。艦名は「峰にかかる雲」に由来する。日本の艦艇としては旧海軍朝潮型駆逐艦8番艦「峯雲」に続き2代目。"
            },
            {
                "datetime": "2025年04月03日 05時の問題",
                "url": "https://ja.wikipedia.org/?curid=1330694",
                "title": "戊戌夢物語",
                "text": "〇〇は、高野長英が1838年（天保9年）にモリソン号事件などについて著した書。『夢物語』『ゆめもの語』とも。「戊戌」は著した年の干支にちなむ。"
            },
            {
                "datetime": "2025年04月03日 04時の問題",
                "url": "https://ja.wikipedia.org/?curid=4786959",
                "title": "佐呂間別川",
                "text": "〇〇は、北海道東部のオホーツク総合振興局管内を流れ、オホーツク海に注ぐ二級河川である。北海道の二級河川では最大であり、北海道最大の湖であるサロマ湖も水系に含まれる。流域の一部は網走国定公園に属する。"
            },
            {
                "datetime": "2025年04月03日 03時の問題",
                "url": "https://ja.wikipedia.org/?curid=1997666",
                "title": "今夜は楽しまナイト",
                "text": "〇〇は、かつて衛星デジタルラジオ、ミュージックバードで放送されていたバラエティ番組である。また、ミュージックバードのコミュニティ放送向けチャンネルを再送信している一部のコミュニティ放送局でも同時生放送されていた。"
            },
            {
                "datetime": "2025年04月03日 02時の問題",
                "url": "https://ja.wikipedia.org/?curid=4691067",
                "title": "森山暁生",
                "text": "〇〇は、徳島県那賀郡羽ノ浦町（現：阿南市）出身のプロ野球選手（投手・育成選手）。左投左打。中日ドラゴンズ所属。"
            },
            {
                "datetime": "2025年04月03日 01時の問題",
                "url": "https://ja.wikipedia.org/?curid=3060525",
                "title": "おひるーな",
                "text": "〇〇は、2014年9月29日から中国放送（RCCラジオ）で放送されていたラジオの生ワイド番組。放送時間は毎週月曜 - 木曜 11:40 - 14:55。"
            },
            {
                "datetime": "2025年04月03日 00時の問題",
                "url": "https://ja.wikipedia.org/?curid=404449",
                "title": "学校保健安全法",
                "text": "〇〇は、学校における児童生徒等および職員の健康の保持増進に関する法律である。法律の目的は第1条を参照。「学校保健法等の一部を改正する法律」（平成20年法律第73号）によって、2009年（平成21年）4月1日、学校保健法から〇〇に改題され、学校における安全管理に関する条項が加えられた。主務官庁は文部科学省初等中等教育局健康教育・食育課で、内閣感染症危機管理統括庁、厚生労働省健康・生活衛生局予防接種課、感染症対策課と連携して執行にあたる。"
            },
            {
                "datetime": "2025年04月02日 23時の問題",
                "url": "https://ja.wikipedia.org/?curid=2597742",
                "title": "東京カランコロン",
                "text": "〇〇は、日本の5人組ロックバンド。2007年に結成、2020年に解散。"
            },
            {
                "datetime": "2025年04月02日 22時の問題",
                "url": "https://ja.wikipedia.org/?curid=1126483",
                "title": "日産・MRエンジン",
                "text": "〇〇は、日産自動車およびルノーの直列4気筒ガソリンエンジンの系列である。"
            },
            {
                "datetime": "2025年04月02日 21時の問題",
                "url": "https://ja.wikipedia.org/?curid=1399573",
                "title": "ネルソン・バルデス",
                "text": "〇〇は、パラグアイ出身の元サッカー選手。現役時代のポジションはフォワード。"
            },
            {
                "datetime": "2025年04月02日 20時の問題",
                "url": "https://ja.wikipedia.org/?curid=3699458",
                "title": "フランクリン・バレト",
                "text": "〇〇は、ベネズエラのカラカス出身のプロ野球選手（内野手）。MLBのボルチモア・オリオールズ傘下所属。右投右打。メディアによっては「バレート」、「バーレト」と表記されることもある。"
            },
            {
                "datetime": "2025年04月02日 19時の問題",
                "url": "https://ja.wikipedia.org/?curid=1635889",
                "title": "倉敷市立琴浦南小学校",
                "text": "〇〇は、岡山県倉敷市児島下の町2丁目（児島地区）にある公立小学校。児島港に面した埋立地に位置する。"
            }
        ]
    }
}