{
    "data": {
        "wiki": [
            {
                "datetime": "2023年10月30日 03時の問題",
                "url": "https://ja.wikipedia.org/?curid=4451899",
                "title": "タイ国鉄RTS型気動車",
                "text": "〇〇は、1971年に営業運転を開始したタイ国有鉄道メークローン線の一般形気動車である。その車番からD9形と呼ばれる場合もある。"
            },
            {
                "datetime": "2023年10月30日 02時の問題",
                "url": "https://ja.wikipedia.org/?curid=2051219",
                "title": "萩野村 (愛知県)",
                "text": "〇〇は、かつて愛知県西春日井郡にあった村。現在の名古屋市北区の中央部（庄内川南岸）にあたり、同区八代町・平手町・中丸町・桝形町・野方通・光音寺町・金城町・水草町・浪打町・萩野通・大野町・辻本通・辻町・天道町・金田町・鳩岡・鳩岡町・安井・安井町・米が瀬町・成願寺・成願寺町・中切町・川中町・福徳町の各一部または全部に相当する。地名としての萩野は「萩野通」（国道41号空港線沿い）として残る。"
            },
            {
                "datetime": "2023年10月30日 01時の問題",
                "url": "https://ja.wikipedia.org/?curid=426834",
                "title": "宇陀警察署",
                "text": "〇〇は、奈良県警察にかつて存在した警察署の一つである。"
            },
            {
                "datetime": "2023年10月30日 00時の問題",
                "url": "https://ja.wikipedia.org/?curid=4781422",
                "title": "シンシア・ジェリ・バイレ",
                "text": "〇〇は、ケニア出身の陸上競技選手。"
            },
            {
                "datetime": "2023年10月29日 23時の問題",
                "url": "https://ja.wikipedia.org/?curid=4472062",
                "title": "フランシス・ウィラビー (第3代ミドルトン男爵)",
                "text": "〇〇は、グレートブリテン貴族。ノッティンガムシャーにおけるトーリー党の指導者としてニューアーク選挙区への影響力を有した。"
            },
            {
                "datetime": "2023年10月29日 22時の問題",
                "url": "https://ja.wikipedia.org/?curid=2979374",
                "title": "東京特許許可局 (テレビドラマ)",
                "text": "〇〇は、NHK教育テレビジョンの番組『天才てれびくん』のドラマ枠にて、2014年4月7日から2015年3月23日まで放送されていたドラマである。"
            },
            {
                "datetime": "2023年10月29日 21時の問題",
                "url": "https://ja.wikipedia.org/?curid=4419463",
                "title": "JR貨物U47A形コンテナ",
                "text": "〇〇は、日本貨物鉄道（JR貨物）輸送用として籍を編入している31 ft私有コンテナ（有蓋コンテナ）である。形式の数字部位「47」は、コンテナの容積を元に決定される。このコンテナ容積47 m3の算出は、厳密には端数四捨五入計算のために、46.5 m3 - 47.4 m3の間に属するコンテナが対象となる。また形式末尾のアルファベット一桁部位「A」は、コンテナの使用用途（主たる目的）が「普通品の輸送」を表す記号として付与されている。1988年（昭和63年）に東急車輛製造にて日本通運所有の最初の1個目が製造され、その後約400個が製作された。複数の所有者、製造ロットにまたがるため形態は様々である。"
            },
            {
                "datetime": "2023年10月29日 20時の問題",
                "url": "https://ja.wikipedia.org/?curid=3261020",
                "title": "シカンダル (カシュミール・スルターン朝)",
                "text": "〇〇は、北インド、カシュミール・スルターン朝の君主（在位：1389年 - 1413年）。その治世、ヒンドゥー教に対する弾圧を加え、ヒンドゥーの寺院や偶像を破壊したため、「偶像破壊者」（Butshikan）と呼ばれた。"
            },
            {
                "datetime": "2023年10月29日 19時の問題",
                "url": "https://ja.wikipedia.org/?curid=57149",
                "title": "アラニンアミノ基転移酵素",
                "text": "〇〇は、GPT（Glutamic Pyruvic Transaminase、グルタミン酸ピルビン酸転移酵素）とも呼ばれ、ピルビン酸とグルタミン酸をアラニンとα-ケトグルタル酸に相互変換する酵素である。人体のほとんどの組織に含まれているが、なかでも肝細胞への分布が圧倒的に多い。そのため、肝細胞の破壊（あるいは細胞膜の透過性亢進）の際には血中濃度が上昇する（逸脱酵素）。"
            },
            {
                "datetime": "2023年10月29日 18時の問題",
                "url": "https://ja.wikipedia.org/?curid=223210",
                "title": "ケータイ刑事 銭形愛",
                "text": "〇〇は、2002年10月6日から2003年3月30日までBS-iで放送されたテレビドラマ。「ケータイ刑事 銭形シリーズ」の第1作目。全26話。主演は宮崎あおい。"
            },
            {
                "datetime": "2023年10月29日 17時の問題",
                "url": "https://ja.wikipedia.org/?curid=52190",
                "title": "神奈川県立スポーツセンター",
                "text": "〇〇は、神奈川県藤沢市善行にある総合スポーツ施設。室内プールや総合体育館、陸上競技場やテニスコートなどを備えている。"
            },
            {
                "datetime": "2023年10月29日 16時の問題",
                "url": "https://ja.wikipedia.org/?curid=2510290",
                "title": "本条村",
                "text": "〇〇は、かつて新潟県北蒲原郡にあった村。"
            },
            {
                "datetime": "2023年10月29日 15時の問題",
                "url": "https://ja.wikipedia.org/?curid=4146766",
                "title": "囲棋少年",
                "text": "〇〇は、中国のテレビアニメーションで、明朝末期の時代に囲碁の才能を持った少年の成長を描く物語。中国中央電視台で2005年に第一部、2009年に第二部、2018年に第三部が制作・放送された。各部は各26回。第一部は囲碁の才能を持った少年江流児の成長とライバルたちとの出会いを描く。第二部では新たなライバル棋鬼王などの人物が登場する。　第三部は2017年にミニブログで、江流児と幼馴染の方百花の成長した姿で予告され，2018年に国家広播電視総局で全52回が公開された。"
            },
            {
                "datetime": "2023年10月29日 14時の問題",
                "url": "https://ja.wikipedia.org/?curid=3530074",
                "title": "1993年の相撲",
                "text": "〇〇は、〇〇関係のできごとについて述べる。"
            },
            {
                "datetime": "2023年10月29日 13時の問題",
                "url": "https://ja.wikipedia.org/?curid=4446748",
                "title": "丸駒温泉",
                "text": "〇〇は、北海道千歳市幌美内にある温泉。"
            },
            {
                "datetime": "2023年10月29日 12時の問題",
                "url": "https://ja.wikipedia.org/?curid=2954450",
                "title": "アルギン酸プロピレングリコール",
                "text": "〇〇は、乳化剤、安定剤および増粘剤に使われる食品添加物である。E番号はE405。化学的には昆布から得られるアルギン酸を、エステル化したものである。カルボキシル基のいくつかはプロピレングリコールとエステル化されており、いくつかはアルカリで中和され、またいくつかは遊離カルボキシル基のままである。"
            },
            {
                "datetime": "2023年10月29日 11時の問題",
                "url": "https://ja.wikipedia.org/?curid=777814",
                "title": "イジー・ヤロシーク",
                "text": "〇〇は、チェコスロバキア（現チェコ）・ウースチー・ナド・ラベム出身の元チェコ代表サッカー選手、現サッカー指導者。ポジションはDF、MF。"
            },
            {
                "datetime": "2023年10月29日 10時の問題",
                "url": "https://ja.wikipedia.org/?curid=1899947",
                "title": "大映京都撮影所",
                "text": "〇〇は、かつて存在した日本の映画スタジオである。1927年（昭和2年）に日本活動写真が「日活太秦撮影所」として開所した。1942年（昭和17年）の戦時統合で設立された大日本映画製作株式会社（のちの大映、現在の角川映画）のもと、同名称となった。1971年（昭和46年）12月の同社の倒産後、1974年（昭和49年）に同社が徳間書店傘下になることで再建、同撮影所は分社化され、株式会社大映映画京都撮影所（-だいえいえいがきょうとさつえいじょ）となり、1986年（昭和61年）4月には完全に閉鎖された。"
            },
            {
                "datetime": "2023年10月29日 08時の問題",
                "url": "https://ja.wikipedia.org/?curid=3592392",
                "title": "タマル・サニキゼ",
                "text": "〇〇は、ジョージアの政治家。2013年7月から2016年6月まで教育科学大臣を務めた。"
            },
            {
                "datetime": "2023年10月29日 07時の問題",
                "url": "https://ja.wikipedia.org/?curid=4148541",
                "title": "正泉寺 (目黒区)",
                "text": "〇〇は、東京都目黒区にある浄土宗の寺院。"
            },
            {
                "datetime": "2023年10月29日 06時の問題",
                "url": "https://ja.wikipedia.org/?curid=526055",
                "title": "レーサーX",
                "text": "〇〇は、アメリカ・カリフォルニア州・ロサンゼルスで結成されたヘヴィメタルバンド。"
            },
            {
                "datetime": "2023年10月29日 05時の問題",
                "url": "https://ja.wikipedia.org/?curid=4818134",
                "title": "清水由紀 (心理学者)",
                "text": "〇〇は、日本の心理学者。専門は発達心理学、文化心理学。早稲田大学文学学術院教授。日本教育心理学会城戸奨励賞受賞。"
            },
            {
                "datetime": "2023年10月29日 04時の問題",
                "url": "https://ja.wikipedia.org/?curid=696082",
                "title": "青山玲子",
                "text": "〇〇は、日本の元モデル、女優、タレントである。北海道出身。プラチナムプロダクションに所属していた。愛称は、れいちゃん。"
            },
            {
                "datetime": "2023年10月29日 03時の問題",
                "url": "https://ja.wikipedia.org/?curid=237026",
                "title": "北鹿沼駅",
                "text": "〇〇は、栃木県鹿沼市玉田町にある東武鉄道日光線の駅である。駅番号はTN 19。"
            },
            {
                "datetime": "2023年10月29日 02時の問題",
                "url": "https://ja.wikipedia.org/?curid=3701428",
                "title": "東京ミッドタウン日比谷",
                "text": "〇〇は、東京都千代田区有楽町一丁目にある複合商業ビルである。三井不動産が手掛ける東京都心部における複合用途型の街づくりブランド「東京ミッドタウン」の第2弾として開発され、2018年3月29日にオープンした。"
            },
            {
                "datetime": "2023年10月29日 01時の問題",
                "url": "https://ja.wikipedia.org/?curid=4840623",
                "title": "処置時の鎮静・鎮痛",
                "text": "〇〇は、患者に処置を行うために、鎮静・解離作用のある薬を、通常は鎮痛薬とともに投与する医療行為である。全体的な目標は、患者の自力呼吸能力を維持しながら、意識レベルを低下させることである。このプロセスでは気道保護反射は損なわれないため、気管挿管は必要ない。PSAは手術室だけでなく、救急診療でもよく行われる。旧来は意識下鎮静（英: conscious sedation）や処置時の鎮静（英: procedural sedation）と呼ばれていたが、鎮痛の重要性が近年認識され、PSAという呼び名が普及しつつある。"
            },
            {
                "datetime": "2023年10月29日 00時の問題",
                "url": "https://ja.wikipedia.org/?curid=4740923",
                "title": "伊織羽音",
                "text": "〇〇は、日本のAV女優。アトラクティブ所属。長野県出身。"
            },
            {
                "datetime": "2023年10月28日 23時の問題",
                "url": "https://ja.wikipedia.org/?curid=4579382",
                "title": "どんちっち",
                "text": "〇〇は、島根県浜田市における石見神楽の通称。浜田市や市産品などをピーアールするためのブランド名などとしてよく用いられる言葉でもある（商標登録番号4688190）。"
            },
            {
                "datetime": "2023年10月28日 22時の問題",
                "url": "https://ja.wikipedia.org/?curid=1291646",
                "title": "メアリー・フレイザー＝タイトラー",
                "text": "〇〇は、イギリスの女流工芸家、デザイナー、ならびに社会改良家。（作品の画像は英語版ウィキペディアで見られる）"
            },
            {
                "datetime": "2023年10月28日 21時の問題",
                "url": "https://ja.wikipedia.org/?curid=4269729",
                "title": "坂本男足",
                "text": "〇〇は、奈良時代の貴族。姓は朝臣。官位は従五位下・隠岐守。"
            },
            {
                "datetime": "2023年10月28日 20時の問題",
                "url": "https://ja.wikipedia.org/?curid=2298606",
                "title": "DOIS SOL",
                "text": "〇〇は、村瀬克俊による日本のサッカー漫画。『週刊少年ジャンプ』にて、2011年11号から同年28号まで連載された。"
            },
            {
                "datetime": "2023年10月28日 19時の問題",
                "url": "https://ja.wikipedia.org/?curid=711391",
                "title": "月影四郎",
                "text": "〇〇は、元プロレスラー。本名：高木 清晴（たかぎ きよはる）。奈良県出身。"
            },
            {
                "datetime": "2023年10月28日 18時の問題",
                "url": "https://ja.wikipedia.org/?curid=4353002",
                "title": "日本ウイグル国会議員連盟",
                "text": "〇〇は、日本の超党派の議員連盟。新疆ウイグル自治区における中華人民共和国政府による人権侵害に問題意識を持つ国会議員により設立された。2012年に設立されたが2020年11月まで休眠状態にあった。2021年2月までは自民党の議連であったが、それ以降より超党派となった。"
            },
            {
                "datetime": "2023年10月28日 17時の問題",
                "url": "https://ja.wikipedia.org/?curid=3327122",
                "title": "超空自衛隊",
                "text": "〇〇は、富永浩史によって書かれた架空戦記・SF小説のシリーズ。自衛隊・災害派遣部隊がタイムスリップに巻き込まれたことによる、第二次世界大戦中での日本軍との共闘を中心に描いている。"
            },
            {
                "datetime": "2023年10月28日 16時の問題",
                "url": "https://ja.wikipedia.org/?curid=835713",
                "title": "テレスコープアレイ実験",
                "text": "〇〇は、超高エネルギー宇宙線を高精度で検出するための実験計画のことである。アメリカ合衆国ユタ州ミラード郡の760km2の範囲に576台のシンチレーション検出器を設置、その周囲3箇所に大気蛍光を検出するための反射望遠鏡（大気蛍光望遠鏡）が1箇所につき12台ずつ設置された。"
            },
            {
                "datetime": "2023年10月28日 15時の問題",
                "url": "https://ja.wikipedia.org/?curid=3757932",
                "title": "木村岳風",
                "text": "〇〇は、日本の吟詠家。本名は松木 利次（まつき としつぐ）。日本詩吟学院の創設者で、近代吟詠の祖と称される。著書に『皇漢名詩の吟じ方』などがある。"
            },
            {
                "datetime": "2023年10月28日 14時の問題",
                "url": "https://ja.wikipedia.org/?curid=3766644",
                "title": "フランチェスコ・マリア・グアッツォ",
                "text": "〇〇は、イタリアの司祭で、『悪行要論』の著者。『悪行要論』は『魔女に与える鉄槌』と比較されるほど有数の魔女関連文献となったが、グアッツォ自身は魔女裁判を監督せず、尋問もしなかったためか、ニコラ・レミやジャン・ボダンほど当時の名声を手にしなかった。マルティン・ルターは悪魔から生まれた子であると主張したルドヴィコ・マリア・シニストラリと同じように、ルターを魔王と女信者の結合により生まれたと断定している。"
            },
            {
                "datetime": "2023年10月28日 13時の問題",
                "url": "https://ja.wikipedia.org/?curid=650876",
                "title": "磯崎亜紀子",
                "text": "〇〇は、主に1980年代に活躍した日本の元女優、元子役である。本名同じ。所属事務所は、劇団日本児童→アートマン工房→蛭川企画→円谷プロダクション。"
            },
            {
                "datetime": "2023年10月28日 12時の問題",
                "url": "https://ja.wikipedia.org/?curid=1022204",
                "title": "大井高等学校",
                "text": "〇〇は、日本の公立高等学校。埼玉県埼玉県立〇〇神奈川県神奈川県立〇〇"
            },
            {
                "datetime": "2023年10月28日 11時の問題",
                "url": "https://ja.wikipedia.org/?curid=495255",
                "title": "紀元前653年",
                "text": "〇〇は、西暦（ローマ暦）による年。紀元前1世紀の共和政ローマ末期以降の古代ローマにおいては、ローマ建国紀元101年として知られていた。紀年法として西暦（キリスト紀元）がヨーロッパで広く普及した中世時代初期以降、この年は〇〇と表記されるのが一般的となった。"
            }
        ]
    }
}