{
    "data": {
        "wiki": [
            {
                "datetime": "2025年03月23日 05時の問題",
                "url": "https://ja.wikipedia.org/?curid=1189805",
                "title": "福田紀一",
                "text": "〇〇は、日本の小説家。元大阪工業大学教授。"
            },
            {
                "datetime": "2025年03月23日 04時の問題",
                "url": "https://ja.wikipedia.org/?curid=3256779",
                "title": "2015 ワールドポート・トーナメント オランダ代表",
                "text": "〇〇は、2015年にオランダで開催された第15回ワールドポート・トーナメントに出場したオランダ代表である。"
            },
            {
                "datetime": "2025年03月23日 03時の問題",
                "url": "https://ja.wikipedia.org/?curid=3633793",
                "title": "A Mirage In The Sun",
                "text": "〇〇は、2015年7月29日に発売されたMONOEYESの1枚目のオリジナルアルバム。"
            },
            {
                "datetime": "2025年03月23日 02時の問題",
                "url": "https://ja.wikipedia.org/?curid=3892134",
                "title": "林下詩美",
                "text": "〇〇は、日本の女性プロレスラー。鹿児島県奄美市出身。マリーゴールド所属。血液型O型。166cm、65kg。柔道初段。"
            },
            {
                "datetime": "2025年03月23日 01時の問題",
                "url": "https://ja.wikipedia.org/?curid=1630160",
                "title": "ミドルズブラ",
                "text": "〇〇は、イングランド北部のノース・ヨークシャー（North Yorkshire）のタウンかつバラかつ単一自治体。ティーズ川の南側に位置する。1829年に6人のクエーカー教徒の組合がティーズ川のほとりに共同で500エーカーの農地を買い、格子状の街区を設定し1830年に着工された、イギリスでは数少ない計画的に作られた都市である。その後製鉄の町として発展した。"
            },
            {
                "datetime": "2025年03月23日 00時の問題",
                "url": "https://ja.wikipedia.org/?curid=159582",
                "title": "司馬穰苴",
                "text": "〇〇は、中国春秋時代の斉の将軍。姓は嬀、氏は田、諱は穰苴。斉の景公に仕えて大司馬となったので氏を司馬と称した（この記事中では〇〇で統一する）。宰相晏嬰の推薦により登用され、斉の繁栄に功績を挙げた。兵法書『司馬法』の著者。田完の後裔である。"
            },
            {
                "datetime": "2025年03月22日 23時の問題",
                "url": "https://ja.wikipedia.org/?curid=3740133",
                "title": "ガルフカップ1972",
                "text": "〇〇は、1972年3月16日から3月28日にかけて、サウジアラビアで開催された第2回目のガルフカップである。クウェートが2回目の優勝を果たした。バーレーンもこの大会に参加したが、サウジアラビアとの試合で審判に抗議したため大会から追放され、バーレーンに関する試合は全て無効となった。"
            },
            {
                "datetime": "2025年03月22日 22時の問題",
                "url": "https://ja.wikipedia.org/?curid=2060489",
                "title": "冷たいギフト/貫通",
                "text": "〇〇は、日本のバンドゆらゆら帝国の5枚目のシングルである。2002年11月20日発売。発売元はユニバーサルミュージック。"
            },
            {
                "datetime": "2025年03月22日 21時の問題",
                "url": "https://ja.wikipedia.org/?curid=1127971",
                "title": "白石城 (伯耆国)",
                "text": "〇〇は、鳥取県東伯郡湯梨浜町白石・方地（ほうじ）にあった日本の城。"
            },
            {
                "datetime": "2025年03月22日 20時の問題",
                "url": "https://ja.wikipedia.org/?curid=230329",
                "title": "渡辺顗修",
                "text": "〇〇は、日本の法学者・言語学者・弁護士。甲南大学大学院教授・甲南大学法科大学院長。博士（法学）。専門は刑事訴訟法。"
            },
            {
                "datetime": "2025年03月22日 19時の問題",
                "url": "https://ja.wikipedia.org/?curid=3441324",
                "title": "要支援児童",
                "text": "〇〇は、児童福祉法に基づいた養育上の支援を要する児童で、児童福祉法第6条の3第5項に定義される。"
            },
            {
                "datetime": "2025年03月22日 18時の問題",
                "url": "https://ja.wikipedia.org/?curid=3380347",
                "title": "Google DeepMind",
                "text": "〇〇は、イギリスにある人工知能を開発しているAlphabetの子会社である。2010年にDeepMind Technologiesとして起業され、2014年にGoogleによって買収された。ロンドンを拠点とし、カナダ、フランス、米国にも研究センターを持つ。2015年、Googleの親会社であるAlphabetの完全子会社となり、2023年4月にはGoogle AIのGoogle Brain部門と統合し、〇〇に名称変更した。 〇〇は、人間と似たようなやり方でどのようにビデオゲームをプレーするかを学ぶニューラルネットワークを作成している。また、従来的なチューリング機械のように外部記憶装置にアクセスできるニューラルネットワークを作成しており、これによって人間の脳の短期記憶を模倣できるのではないかと期待されている。DeepMindが開発したプログラムAlphaGoは人間のプロ囲碁棋士を初めて破った。"
            },
            {
                "datetime": "2025年03月22日 17時の問題",
                "url": "https://ja.wikipedia.org/?curid=5028244",
                "title": "白糸トンネル",
                "text": "〇〇は、北海道島牧郡島牧村オコツナイから同村栄浜を結ぶ国道229号のトンネル。"
            },
            {
                "datetime": "2025年03月22日 16時の問題",
                "url": "https://ja.wikipedia.org/?curid=2903323",
                "title": "マット・マギル",
                "text": "〇〇は、アメリカ合衆国カリフォルニア州ベンチュラ郡シミバレー出身の元プロ野球選手（投手）。右投右打。"
            },
            {
                "datetime": "2025年03月22日 15時の問題",
                "url": "https://ja.wikipedia.org/?curid=1318115",
                "title": "MIX (プログラミング)",
                "text": "〇〇は、ドナルド・クヌースが著書 The Art of Computer Programming (TAoCP) で使った仮想計算機である。1960年代に生まれた 〇〇は、今後の TAoCP の版では M〇〇という新たな（仮想の）コンピュータアーキテクチャで置換される予定である。〇〇と M〇〇のソフトウェア実装（MIXware および MMIXware）はクヌースが開発しており、自由に利用可能となっている。クヌースの MIX/M〇〇エミュレータからの派生版も存在する。GNU MDK がその一例で、自由ソフトウェアとして幅広いプラットフォーム上で動作する。TAoCP 本文中の記述によれば、〇〇は「世界初の多機種複合型コンピュータ」で、型番は 〇〇という綴りをローマ数字として解釈したものと同じ 1009 であると設定されている。この数は「〇〇によく似ていて 〇〇を簡単にシミュレートできる実在のコンピュータ 16 種」の型番から取って平均した（mixした）ものであるとあるが、具体的にその機種を検討してみるとかなり恣意的であり、このラインナップについてはこじつけと見てよいであろう。"
            },
            {
                "datetime": "2025年03月22日 14時の問題",
                "url": "https://ja.wikipedia.org/?curid=2536248",
                "title": "イオンモール船橋",
                "text": "〇〇は、千葉県船橋市山手一丁目に所在し、イオンリテール株式会社が開発、イオンモール株式会社が運営しているショッピングセンター。イオンリテールが「イオンモール」の名称でSCを新規開業する初の施設となる。"
            },
            {
                "datetime": "2025年03月22日 13時の問題",
                "url": "https://ja.wikipedia.org/?curid=3032840",
                "title": "東関庄助",
                "text": "〇〇は、現在の栃木県足利市（下野国安蘇郡）出身で東関部屋に所属した力士。本名は東関 庄助（旧名は不明）。5代東関。身長、体重不明。最高位は東関脇。"
            },
            {
                "datetime": "2025年03月22日 12時の問題",
                "url": "https://ja.wikipedia.org/?curid=156101",
                "title": "単体 (数学)",
                "text": "〇〇は、「r ≤ n ならばどの r + 1 個の点も r − 1 次元の超平面に同時に含まれることのない」ような n + 1 個の点からなる集合の凸包のことで、点・線分・三角形・四面体・五胞体といった基本的な図形の n 次元への一般化である。全ての辺の長さが等しい時、正単体と言う。単体は、頂点の位置さえ決めればそれのみによって一意的に決定される。さらに単体は単体的複体や鎖複体などの概念を与えるが、これらはさらに抽象化されて、幾何学を組合せ論的あるいは代数的に扱う道具となる。また逆に、抽象化された複体の概念から単体が定義される。"
            },
            {
                "datetime": "2025年03月22日 11時の問題",
                "url": "https://ja.wikipedia.org/?curid=1119598",
                "title": "サムライ (沢田研二の曲)",
                "text": "〇〇は、沢田研二の22枚目のシングル。1978年1月21日にポリドール・レコードより発売された。"
            },
            {
                "datetime": "2025年03月22日 10時の問題",
                "url": "https://ja.wikipedia.org/?curid=115983",
                "title": "ポール牧",
                "text": "〇〇は、日本のコメディアン、タレント、俳優、元僧侶。北海道天塩郡天塩町出身。実家は曹洞宗寺院。北海道天塩高等学校卒業。血液型はAB型。本名は榛澤一道（はんざわ かずみち）。僧名は熈林一道（きりん いちどう）。関武志とともにコント・ラッキー7を結成し、人気を博した。リズム良く指を鳴らす「指パッチン」で知られた。"
            },
            {
                "datetime": "2025年03月22日 09時の問題",
                "url": "https://ja.wikipedia.org/?curid=167416",
                "title": "ジュリア・クリステヴァ",
                "text": "〇〇は、ブルガリア出身のフランスの文学理論家で、著述家、哲学者、精神分析家。ユダヤ系の家庭に生まれた。"
            },
            {
                "datetime": "2025年03月22日 08時の問題",
                "url": "https://ja.wikipedia.org/?curid=194178",
                "title": "疾風同心",
                "text": "〇〇は、その『八丁堀暴れ軍団』についても併せて記述する。"
            },
            {
                "datetime": "2025年03月22日 07時の問題",
                "url": "https://ja.wikipedia.org/?curid=2312492",
                "title": "高田カトリック幼稚園",
                "text": "〇〇は、奈良県大和高田市にある、私立の幼稚園である。設置者は学校法人カトリックマリスト会学園。"
            },
            {
                "datetime": "2025年03月22日 06時の問題",
                "url": "https://ja.wikipedia.org/?curid=365944",
                "title": "夜桜銀次",
                "text": "〇〇は、20世紀に活動した日本のヤクザ。暴力団・三代目山口組 石井組組員（舎弟）。大分県由布市出身。本名は平尾 国人。全身に夜桜の咲き乱れる刺青をしていたことからこの呼び名がついた。"
            },
            {
                "datetime": "2025年03月22日 05時の問題",
                "url": "https://ja.wikipedia.org/?curid=850325",
                "title": "ハナトガリガエル",
                "text": "〇〇は、両生綱無尾目アカガエル科〇〇属に分類されるカエル。本種のみでハナトガリカエル属を形成する。別名ソロモンコノハガエル、ソロモンツノガエル。"
            },
            {
                "datetime": "2025年03月22日 04時の問題",
                "url": "https://ja.wikipedia.org/?curid=2376240",
                "title": "新町 (西東京市)",
                "text": "〇〇は、東京都西東京市の町。現行行政地名では新町一丁目から新町六丁目までの6町が存在する。住居表示実施済み地区。郵便番号は202-0023。"
            },
            {
                "datetime": "2025年03月22日 03時の問題",
                "url": "https://ja.wikipedia.org/?curid=100565",
                "title": "森島寛晃",
                "text": "〇〇は、広島県広島市南区出身の元プロサッカー選手。現役時代のポジションはミッドフィールダー（オフェンシブハーフ）、フォワード（セカンドトップ）。1998年、2002年のFIFAワールドカップメンバー。現在はセレッソ大阪運営会社「株式会社セレッソ大阪」代表取締役社長を務める。「日本一腰の低いJリーガー」といわれた。Jリーグの開幕連続得点記録保持者（7試合連続）、オールスターゲーム最多得点記録保持者（通算6ゴール。2024年現在、オールスターゲームは事実上廃止状態にある）。現役時代にはリーグ戦だけで140得点を記録した（セレッソ在籍時に最も得点を取った選手）。"
            },
            {
                "datetime": "2025年03月22日 02時の問題",
                "url": "https://ja.wikipedia.org/?curid=2695657",
                "title": "青山周平 (政治家)",
                "text": "〇〇は、日本の政治家。自由民主党所属の元衆議院議員（4期）。文部科学副大臣、文部科学大臣政務官兼内閣府大臣政務官兼復興大臣政務官を歴任。"
            },
            {
                "datetime": "2025年03月22日 01時の問題",
                "url": "https://ja.wikipedia.org/?curid=551656",
                "title": "ゆかにっし",
                "text": "〇〇は、荒井チェリーによる日本の4コマ漫画作品。『まんがタイム』（芳文社）にて、2004年4月号から2006年3月号まで連載。2016年5月に刊行された荒井の傑作集『Cherry etc.荒井チェリー傑作集』上巻に、本作が収録されている。"
            },
            {
                "datetime": "2025年03月22日 00時の問題",
                "url": "https://ja.wikipedia.org/?curid=1621624",
                "title": "教育社歴史新書",
                "text": "〇〇は、教育社（現・キョーイクソフト）が発行していた新書シリーズ。日本史シリーズと東洋史シリーズと西洋史シリーズの三つがあった。1977年（昭和52年）から1991年（平成3年）まで、初期は毎月刊行されていた。すべて書き下ろしであり、一つ一つのテーマごとで一冊の本にし、大掴みできることができるようにした入門書、教養書である。時代ごとに区切られてはいるが、通史ではないので、それぞれ独立して読めるようになっている。その後、講談社学術文庫やちくま学芸文庫で再刊されたものもある。"
            },
            {
                "datetime": "2025年03月21日 23時の問題",
                "url": "https://ja.wikipedia.org/?curid=1487577",
                "title": "ケイレブ・ストロング",
                "text": "〇〇は、アメリカ合衆国の弁護士、政治家。1800年から1807年及び1812年から1816年までマサチューセッツ州知事を務めた。"
            },
            {
                "datetime": "2025年03月21日 22時の問題",
                "url": "https://ja.wikipedia.org/?curid=2548931",
                "title": "生徒会探偵キリカ",
                "text": "〇〇は、漫画版が『月刊少年シリウス』（講談社）にて2012年6月号より2015年5月号→Web漫画ページ『水曜日のシリウス』にて2015年4月23日から2015年11月25日までYUIの作画で連載され、シリウスKCより刊行された。2014年4月から2015年5月まで『水曜日のシリウス』にて、スピンオフ漫画『〇〇たちの日常』が福田直叶の作画にて連載された。また海外においては、尖端出版（台湾）より小説翻訳版が2012年11月より刊行されている。"
            },
            {
                "datetime": "2025年03月21日 21時の問題",
                "url": "https://ja.wikipedia.org/?curid=1640035",
                "title": "ユーリー・イヴァノヴィチ (ドミトロフ公)",
                "text": "〇〇は、イヴァン3世の三男、母はモレアス専制公ソマス・パレオロゴスの娘でビザンツ皇族出身のゾエ・パレオロギナ（ソフィヤ）。ドミトロフなどを分領として与えられた。"
            },
            {
                "datetime": "2025年03月21日 20時の問題",
                "url": "https://ja.wikipedia.org/?curid=1788431",
                "title": "ルーテラ (小惑星)",
                "text": "〇〇は、小惑星帯の小惑星である。アルノルト・シュヴァスマンがベルゲドルフのハンブルク天文台で発見した。ドイツの天文学者、ロベルト・ルターに因んで名付けられた。2004年4月に新潟県で掩蔽が観測された。"
            },
            {
                "datetime": "2025年03月21日 19時の問題",
                "url": "https://ja.wikipedia.org/?curid=1615626",
                "title": "N821i",
                "text": "〇〇は、日本電気(NEC)のNTTドコモの第二世代携帯電話(mova)・PHS（ドッチーモ）端末である。"
            },
            {
                "datetime": "2025年03月21日 18時の問題",
                "url": "https://ja.wikipedia.org/?curid=2607360",
                "title": "かよえ!チュー学",
                "text": "〇〇は、東海テレビで放送されていた5分枠の短編アニメーション。略称は、「かよチュー」。"
            },
            {
                "datetime": "2025年03月21日 17時の問題",
                "url": "https://ja.wikipedia.org/?curid=1436132",
                "title": "都営バス青戸支所",
                "text": "〇〇は、東京都葛飾区白鳥の水戸街道沿いにある都営バスの営業所（支所）で、葛飾区、墨田区、台東区の水戸街道・浅草通り周辺を走る路線を担当し、上23・上26系統など一部路線では江東区や江戸川区まで運行されている。正式名称は、東京都交通局南千住自動車営業所青戸支所で、営業所記号はZを用いる。ナンバーは足立と葛飾である。当支所の運行業務は、2006年4月1日以降はとバスに運営が委託されており、直営の組織ではなくなっているが、現在も都営バスの車庫としては存続している。"
            },
            {
                "datetime": "2025年03月21日 16時の問題",
                "url": "https://ja.wikipedia.org/?curid=446348",
                "title": "デイヴ・コーズ",
                "text": "〇〇は、アメリカ合衆国のフュージョン・サックス奏者。"
            },
            {
                "datetime": "2025年03月21日 15時の問題",
                "url": "https://ja.wikipedia.org/?curid=4004382",
                "title": "バサースト伯爵",
                "text": "〇〇は、グレートブリテン貴族の伯爵位。トーリー党の政治家の初代バサースト男爵アレン・バサーストが1772年に叙されたのに始まる。"
            },
            {
                "datetime": "2025年03月21日 14時の問題",
                "url": "https://ja.wikipedia.org/?curid=4450056",
                "title": "四臭化テルル",
                "text": "〇〇は、化学式TeBr4の無機化合物である。四塩化テルルと似た四量体構造を持つ。臭素とテルルの反応で得られる。〇〇の蒸気は、次のように解離する。TeBr4 → TeBr2 + Br2融解状態では導体であり、陽イオンTeBr3+と陰イオンBr-に解離する。ベンゼンやトルエンに溶けると、非イオン化四量体Te4Br16として存在する。アセトニトリルのようなドナー性溶媒の中では、CH3CNイオン錯体が形成され、溶液は導体になる。TeBr4 + 2CH3CN → (CH3CN)2TeBr3+ + Br−"
            }
        ]
    }
}